Workbook
Name lista: Alumnos!$A:$XES

Sheet Verano2024
A1: Marca temporal | B1: Dirección de correo electrónico | C1: Nombre completo | D1: Correo Electrónico | E1: Edad | F1: DNI | G1: Domicilio (localidad) | H1: Cel de contacto | I1: Talleres | J1: Abonar inscripción Alias: folklore.ma (Titular: Graciela Silva)
A2: 45317.679 | B2: luchagana1@gmail.com | C2: Gianna victoria viera troil | D2: Luchagana1@gmail.com | E2: 6 | F2: 56719844 | G2: Astrada 508 | H2: 3754401018 | I2: Manualidades para niños | J2: Alias: avance.giro.final (titular: Graciela Silva)
A3: 45317.683 | B3: luchagana1@gmail.com | C3: Luana sherlyn viera troil | D3: Luchagana1@gmail.com | E3: 9 | F3: 56637457 | G3: Astrada 508 | H3: 3754401018 | I3: Manualidades para niños | J3: Alias: avance.giro.final (titular: Graciela Silva)
A4: 45319.479 | B4: carogo12mez3@gmail.com | C4: Caarolina Ines Gomez | D4: carogo12mez3@gmail.com | E4: 26 | F4: 40410777 | G4: Calle córdoba 519, Leandro N Alem | H4: 3754495541 | I4: Corte y confección
A5: 45319.546 | B5: veronicagalarza705@gmail.com | C5: Veronica galarza | D5: Veronicagalarza705@gmail.com | E5: 30 | F5: 36470561 | G5: Calle el paraiso lote1 mz R | H5: 3754525043 | I5: Corte y confección
A6: 45321.375 | B6: mbareteviajesevt@gmail.com | C6: Dana milagros Diaz Martin | D6: mbareteviajesevt@gmail.com | E6: 15 | F6: 48889747 | G6: Corrientes 139 Leandro N Alem | H6: 3754528106 | I6: Canto
A7: 45322.808 | B7: guazzitizziano@gmail.com | C7: Emma Valentina Guazzi | D7: guazzitizziano@gmail.com | E7: 9 años | F7: 53790456 | G7: Barrio Virgen del Rosario W 5 | H7: 3704-810796 | I7: Manualidades para niños
A8: 45322.865 | B8: pedrozovivilore@gmail.com | C8: Balanda Leandro Miguel | D8: pedrozovivilore@gmail.com | E8: 11 años | F8: 52064374 | G8: Picada primero de mayo Lote 28 | H8: 3754-508532 | I8: Canto
A9: 45329.754 | B9: fernandarojasrios37@gmail.com | C9: Martina Florencia Rios | D9: fernandarojasrios37@gmail.com | E9: 12 | F9: 50940985 | G9: El Jacarandá 15 Alem | H9: 3755671228 | I9: Canto | J9: Si
A10: 45344.458 | B10: giselaalvez_15@hotmail.com | C10: Gisela Antonieta Alvez | D10: giselaalvez_15@hotmail.com | E10: 34 | F10: 34422662 | G10: Leandro. N. Alem | H10: 3754441492 | I10: Canto

Sheet Recibos
B1: ORIGINAL
G3: RECIBO
G4: Punto de Vta: 00002 Comp. Nro: | L4: ="0000"&COUNT(G43:G53)+1 -> 00002
B5: Razón Social: SILVA GRACIELA BEATRIZ | G5: Fecha de Emisión: | K5: =TODAY() -> 46197
B6: Domicilio Comercial: Cataratas Del Iguazú 912 - Leandro N. Alem | G6: CUIT: 27-25496483-8
C7: Misiones | G7: Ing. Brutos: 27-25496483-8
B8: Condición frente al IVA: Responsable Monotributo | G8: Inicio Actividades: 01/10/2020
B9: Documento no válido como Factura
B10: Alumno: | C10: Francisco Nestor | K10: DNI: | L10: =VLOOKUP(C10,formulario!C1:R1006,14,0) -> 55046930
B11: Domicilio: | C11: =VLOOKUP(C10,formulario!C1:J1006,4,0) -> Mecking 256 | K11: Teléfono: | L11: =VLOOKUP(C10,formulario!C1:J1006,5,0) -> 3754456868
B12: Nro de CUIT: | C12: =VLOOKUP(C10,formulario!C1:N1006,10,0) -> 34515584
B14: Mes | C14: Detalle / Servicio | L14: Importe
B16: Junio | C16: Servicios de Enseñanza Artística mes de: | F16: =B16& " 2026" -> Junio 2026 | L16: 25000
C17: Inscripción | L17: 20000
L27: =IF(B27="","",K27)
B29: Importe Total | K29: Pesos | L29: =SUM(L16:L28) -> 45000
B30: Cataratas del Iguazú 912 - Leandro N. Alem - Mnes. C.P. 3315 - Info: 3754 406435 / 499750
B36: Asunto: | C36: Recibo Instituto Superior de Danzas Folkloricas Argentinas
B37: Mensaje: | C37: ="Hola, "&G12&" “Como las hojas en otoño que caen para volver a renacer, cada paso en la danza folklórica guarda la memoria de quienes vinieron antes… y la fuerza de quienes siguen bailando hoy. 🍂💃" -> Hola, “Como las hojas en otoño que caen para volver a renacer, cada paso en la danza folklórica guarda la memoria de quienes vinieron antes… y la fuerza de quienes siguen bailando hoy. 🍂💃
B38: Destinatario: | C38: =VLOOKUP(C10,formulario!C1:J1006,2,0) -> neguikpp@gmail.com
B40: =K5 -> 46197 | C40: =C10 -> Francisco Nestor | D40: =B16 -> Junio | E40: =K5 -> 46197 | F40: =C17 -> Inscripción | G40: =L29 -> 45000
C43: =IFERROR(__xludf.DUMMYFUNCTION("filter(Pagos!B:F,C10=Pagos!B:B)"),"Francisco Nestor ") -> Francisco Nestor | D43: =IFERROR(__xludf.DUMMYFUNCTION("""COMPUTED_VALUE"""),"Junio") -> Junio | E43: =IFERROR(__xludf.DUMMYFUNCTION("""COMPUTED_VALUE"""),46196.0) -> 46196 | F43: =IFERROR(__xludf.DUMMYFUNCTION("""COMPUTED_VALUE"""),"Inscripción") -> Inscripción | G43: =IFERROR(__xludf.DUMMYFUNCTION("""COMPUTED_VALUE"""),45000.0) -> 45000

Sheet IDeIn
B1: ORIGINAL
G3: RECIBO
G4: Punto de Vta: 00002 Comp. Nro: | L4: ="0000"&COUNT(G32:G39)+1 -> 00001
B5: Razón Social: TURCHEÑUK PEDRO | G5: Fecha de Emisión: | K5: =TODAY() -> 46197
B6: Domicilio Comercial: Cataratas Del Iguazú 912 - Leandro N. Alem | G6: CUIT: 20-2309985-2
C7: Misiones | G7: Ing. Brutos: 20-23099805,2
B8: Condición frente al IVA: Responsable Monotributo | G8: Inicio Actividades: 01/03/1997
B9: Documento no válido como Factura
B10: Cliente: | C10: Instituto Santiago Canclini | K10: DNI:
B11: Domicilio: | C11: Maipu 1350 | K11: Teléfono:
B12: Nro de CUIT:
B14: Cantidd | C14: Detalle / Servicio | L14: Importe
B16: 2 | C16: armados e instalacion de CPU, Rizen | L16: 100000
B17: 2 | C17: Instalacion de 2 discos SSD 120Gb + instalación de sistema Operativo y Office | L17: 90000
L27: =IF(B27="","",K27)
B29: Importe Total | K29: Pesos | L29: =SUM(L16:L28) -> 190000
B30: Cataratas del Iguazú 912 - Leandro N. Alem - Mnes. C.P. 3315 - Info: 3754 406435 / 499750

Sheet ISC
A1: $ 100.000 secundaria | C1: Recibo X Nº1 | D1: 100000
A2: $ 90.000 primaria | C2: Recibo X Nº1 | D2: 90000
A4: Cuotas | C4: Marzo | D4: Abril | E4: Mayo
A5: $ 65.000 secundaria
A6: $ 60.000 primaria
A8: Material de Elena $ 110.000

Sheet Pagos
A1: 46091 | B1: Candela Jazmín Wach | C1: Marzo | D1: 46091 | E1: (1ra cuota Prof.) | F1: 40000
A2: 46091 | B2: Noa Samara Duran Quensell | C2: Marzo | D2: 46091 | E2: (inscripción y 1ra cuota) | F2: 45000
A3: 46091 | B3: Brenda Anahi Back | C3: Marzo | D3: 46091 | E3: (1ra cuota Prof.) | F3: 40000
A4: 46091 | B4: Alma Milenna Piñeiro | C4: Marzo | D4: 46091 | E4: (Inscripcion y 1ra cuota.) | F4: 45000
A5: 46091 | B5: Gianna Josefina Alarcón francesconi | C5: Marzo | D5: 46091 | E5: (Inscripcion) | F5: 20000
A6: 46091 | B6: Ona Guillermina Arndt | C6: Marzo | D6: 46091 | E6: (Inscripcion) | F6: 20000
A7: 46091 | B7: Gia Amelie | C7: Marzo | D7: 46091 | E7: (Inscripcion) | F7: 20000
A8: 46091 | B8: MELINA AYLÉN FERREIRA | C8: Marzo | D8: 46091 | E8: (Inscripcion) | F8: 20000
A9: 46093 | B9: Ana Paula Dallabrida | C9: Marzo | D9: 46093 | E9: (Inscripcion y 1ra cuota) | F9: 45000
A10: 46118 | B10: VICTORIA MACIEL KREISCHER | C10: Marzo | D10: 46118 | E10: (Inscripcion y 1ra cuota) | F10: 45000
A11: 46118 | B11: Zoe Alexia Frenna | C11: Marzo | D11: 46118 | E11: (Inscripcion y 1ra cuota) | F11: 60000
A12: 46120 | B12: Candela Jazmín Wach | C12: Abril | D12: 46120 | E12: 2da cuota) | F12: 40000
... A16: 46121 | B16: Isabella Hupan | C16: Abril | D16: 46121 | E16: Inscripción | F16: 17500
A17: 46132 | B17: Alma Milenna Piñeiro | C17: Abril | D17: 46132 | F17: 25000
A18: 46133 | B18: Ona Guillermina Arndt | C18: Abril | D18: 46133 | F18: 25000
A19: 46133 | B19: Gia Amelie | C19: Abril | D19: 46133 | F19: 12500
A20: 46133 | B20: Keyla Franco | C20: Marzo | D20: 46133 | E20: inscripción | F20: 40000
A21: 46146 | B21: Alma Milenna Piñeiro | C21: Mayo | D21: 46146 | F21: 25000
A22: 46146 | B22: Sanabria Benjamín Fernando | C22: Mayo | D22: 46146 | F22: 40000
A23: 46146 | B23: Sanabria Benjamín Fernando | C23: Abril | D23: 46146 | E23: Inscripcion | F23: 60000
A24: 46146 | B24: MELINA AYLÉN FERREIRA | C24: Abril | D24: 46146 | F24: 50000
A25: 46147 | B25: Benjamín Maximiliano Losanto | C25: Mayo | D25: 46147 | F25: 20000
A26: 46148 | B26: VICTORIA MACIEL KREISCHER | C26: Mayo | D26: 46148 | F26: 25000
A27: 46148 | B27: Romero Pona Luz Milagros | C27: Mayo | D27: 46148 | F27: 40000
A28: 46160 | B28: Ana Paula Dallabrida | C28: Mayo | D28: 46160 | F28: 25000
A29: 46160 | B29: Ana Paula Dallabrida | C29: Abril | D29: 46160 | F29: 25000
A30: 46174 | B30: VICTORIA MACIEL KREISCHER | C30: Junio | D30: 46174 | F30: 25000
A31: 46174 | B31: Alma Milenna Piñeiro | C31: Junio | D31: 46174 | F31: 25000
A32: 46177 | B32: Isabella Hupan | C32: Abril | D32: 46177 | F32: 25000
A33: 46177 | B33: Rocio Hupan | C33: Abril | D33: 46177 | F33: 25000
A34: 46177 | B34: Sol Betiana Yagus | C34: Junio | D34: 46177 | F34: 25000
A35: 46177 | B35: Sanabria Benjamín Fernando | C35: Junio | D35: 46177 | F35: 40000
... A42: 46181 | B42: Ciro Benjamín Nolasco | C42: Junio | D42: 46181 | F42: 25000
A43: 46196 | B43: Francisco Nestor | C43: Junio | D43: 46196 | E43: Inscripción | F43: 45000

Sheet Alumnos
B1: Apellido y Nombre | C1: Marca temporal | D1: Dirección de correo electrónico | E1: DNI | F1: F. de Nac | G1: Edad | H1: Domicilio | I1: Teléfono | J1: Ocupación | K1: Curso que Elige | L1: Localidad | N1: Matricula | O1: Marzo | P1: Abril | Q1: Mayo | R1: Junio | S1: Julio | T1: Agosto | U1: septiembre | V1: Octubre | W1: Noviembre | X1: Diciembre | Y1: Mes de inicio | Z1: Nro de Cuota | AA1: Dias y horarios de clases | AB1: Nivel
A2: 1 | B2: Alzugaray María Laura | C2: 7/28/2020 | D2: marialaura.alzugaray@gmail.com | E2: 37581526 | F2: 34174 | G2: 28 | H2: Barrio Illia casa N° 84 | I2: 3754472507 | J2: Docente | K2: Danzas Folkóricas Argentinas "Modalidad Acelerado" | L2: Leandro N. Alem | Z2: =COUNT(M2:X2) -> 0 | AA2: Martes y Jueves 18:00 - 20:00 hs | AB2: Segundo Preparatorio
A3: 2 | B3: Da Luz Facundo Manuel | C3: 2/18/2020 | D3: fdaluz83@gmail.com | E3: 30430962 | F3: 12/20/1983 | G3: 37 | H3: Felix Durán 449 | I3: 3754475271 | J3: Asesor crediticio | K3: Danzas Folkóricas Argentinas "Modalidad Acelerado" | L3: Leandro N. Alem | Z3: =COUNT(M3:X3) -> 0 | AA3: Martes y Jueves 18:00 - 20:00 hs | AB3: Primero Preparatorio
A4: 3 | B4: Leguizamón Flavia Beatriz | C4: 44424 | D4: flaviabeatrizleguizamon@gmail.com | E4: 41694880 | F4: 36250 | G4: 22 | H4: Bº Loteo Fao M8 S/n | I4: 3754465397 | K4: Danzas Folkóricas Argentinas "Modalidad Acelerado" | L4: Leandro N. Alem | Z4: =COUNT(M4:X4) -> 0 | AA4: Martes y Jueves 18:00 - 20:00 hs | AB4: Primer Año
A5: 4 | B5: Paniagua Nadia Belen | C5: 7/20/2020 | D5: centroesteticoalmabella@gmail.com | E5: 35006709 | F5: 33085 | G5: 31 | H5: Barrio Illia | I5: 3754461035 | J5: Docente | K5: Danzas Folkóricas Argentinas "Modalidad Acelerado" | L5: Leandro N. Alem | Z5: =COUNT(M5:X5) -> 0 | AA5: Martes y Jueves 18:00 - 20:00 hs | AB5: Segundo Preparatorio
A6: 5 | B6: Pinto Da Silva Florencia Guadalupe | C6: 1/30/2020 | D6: flor85pintodasilva@gmail.com | E6: 31572466 | F6: 31178 | G6: 36 | H6: San martin y fleming s/n | I6: 3754470782 | J6: Profesora de educacion fisica y preceptora | K6: Danzas Folkóricas Argentinas "Modalidad Acelerado" | L6: San Javier | Z6: =COUNT(M6:X6) -> 0 | AA6: Sábados de 08:00 - 12:00 hs | AB6: Tercero Preparatorio
A7: 6 | B7: Rodriguez de Olivera Solange María | C7: 44112 | D7: solangerodriguezdeolivera@gmail.com | E7: 34802897 | F7: 11/22/1990 | G7: 31 | H7: Itacaruaré | I7: 3754524721 | J7: Profesora de Nivel Inicial | K7: Danzas Folkóricas Argentinas "Modalidad Acelerado" | L7: Itacaruaré | Z7: =COUNT(M7:X7) -> 0 | AA7: Sábados de 08:00 - 12:00 hs | AB7: Segundo Preparatorio
A8: 7 | B8: Smorzeniuk yenifer de los angeles | C8: 43959 | D8: yenismorze@gmail.com | E8: 44389892 | F8: 10/13/2002 | G8: 19 | H8: 3 de febrero s/n Itacaruare | I8: 3754400694 | J8: Estudiante | K8: Danzas Folkóricas Argentinas "Modalidad Acelerado" | L8: Itacaruaré | Z8: =COUNT(M8:X8) -> 0 | AA8: Sábados de 08:00 - 12:00 hs | AB8: Segundo Preparatorio
A9: 8 | B9: Da Luz Uriel Ismael | C9: 44419 | D9: fdaluz83@gmail.com | F9: 40995 | G9: 7 | H9: Felix Duran 449 | K9: Danzas Folkóricas Argentinas infantil | L9: Leandro N. Alem | Z9: =COUNT(M9:X9) -> 0 | AA9: Miercoles 16:00 hs | AB9: Inicial
A10: 9 | B10: Llamosas Renata Valentina | C10: 44408 | D10: andreaferreiraa7@gmail.com | E10: 52309302 | F10: 41158 | G10: 9 | H10: Itacaruare | I10: 3754491063 | K10: Danzas Folkóricas Argentinas infantil | L10: Itacaruaré | Z10: =COUNT(M10:X10) -> 0 | AA10: Sabados 14:00 hs | AB10: Inicial
A11: 10 | B11: Losanto Benjamin Maximiliano | C11: 44777 | D11: marcelalosanto@hotmail.com | E11: 53796732 | F11: 41729 | G11: 8 | H11: Calle Bonpland 115 | I11: 3754432414 | K11: Danzas Folkóricas Argentinas infantil | L11: Leandro N. Alem
A12: 11 | B12: Losanto Pedrosky William Nahuel | C12: 44778 | D12: marcelalosanto@hotmail.com | E12: 54716260 | F12: 42151 | G12: 7 | H12: Calle Bonpland 115 | I12: 3754432414 | K12: Danzas Folkóricas Argentinas infantil | L12: Leandro N. Alem | AA12: Miercoles de 17:00 - 18:00 hs | AB12: Primero Preparatorio
A13: 12 | B13: Moschen Lucas Martin | C13: 44409 | D13: marianaalaniz82@gmail.com | E13: 53235744 | F13: 41506 | G13: 7 | H13: Otto Bar 62 | I13: 3755410502 | K13: Danzas Folkóricas Argentinas infantil | L13: Leandro N. Alem | Z13: =COUNT(M13:X13) -> 0 | AA13: Martes 16:00 Hs | AB13: 1er año Taller
A14: 13 | B14: Moschen Paula Antonella | C14: 44409 | D14: marianaalaniz82@gmail.com | E14: 55488253 | F14: 42514 | G14: 5 | H14: Otto Bar 62 | I14: 3755410502 | K14: Danzas Folkóricas Argentinas infantil | L14: Leandro N. Alem | Z14: =COUNT(M14:X14) -> 0 | AA14: Martes 16:00 Hs | AB14: 1er año Taller
A15: 14 | B15: =#REF! -> #REF! | C15: 45051 | D15: =#REF! -> #REF! | E15: =#REF! -> #REF! | F15: =#REF! -> #REF! | G15: =#REF! -> #REF! | H15: =#REF! -> #REF! | I15: =#REF! -> #REF! | K15: Danzas Folkóricas Argentinas infantil | L15: Leandro N. Alem
A16: 15 | B16: Paniagua Alma Isabela | C16: 44635 | D16: carlaasuncion@hotmail.com.ar | E16: 53092518 | F16: 41529 | G16: 8 | H16: Saavedra 112 | I16: 3754436602 | K16: Danzas Folkóricas Argentinas infantil | L16: Leandro N. Alem
A17: 16 | B17: Luz Milagros Pona Romero | C17: 44412 | D17: daniponna@gmail.com | E17: 53536539 | F17: 41600 | G17: 7 | H17: Bº Illia c109 | I17: 3754418757 | K17: Danzas Folkóricas Argentinas infantil | L17: Leandro N. Alem | Z17: =COUNT(M17:X17) -> 0 | AA17: Miercoles 16:00 hs | AB17: Inicial
A18: 17 | B18: Scromeda Dos Santos Abigail Ariadna | C18: 44223 | D18: Noeliads14@gmail.com | E18: 52303419 | F18: 41015 | G18: 9 | H18: Barrio 30 viv Jose Carlos Freaza casa 12 | I18: 3754416242 | K18: Danzas Folkóricas Argentinas infantil | L18: Itacaruaré
A19: 18 | B19: Tucheñuk Helena Anastasia | C19: 44419 | D19: gracielasilvatu3@gmail.com | E19: 53092554 | F19: 41549 | G19: 7 | H19: Cataratas del Iguazú 912 | I19: 3754499750 | J19: Profesora de Folklore | K19: Danzas Folkóricas Argentinas infantil | L19: Leandro N. Alem | Z19: =COUNT(M19:X19) -> 0 | AA19: Miercoles 16:00 hs | AB19: Inicial
A20: 19 | B20: Turcheñuk Josias Pablo | C20: 44419 | D20: ideincom@gmail.com | E20: 50559930 | F20: 40653 | G20: 10 | H20: Cataratas del Iguazú 912 | I20: 3754499750 | J20: Profesora de Folklore | K20: Danzas Folkóricas Argentinas infantil | L20: Leandro N. Alem | Z20: =COUNT(M20:X20) -> 0 | AA20: Miercoles 16:00 hs | AB20: Inicial
A21: 20 | B21: =#REF! -> #REF! | C21: 45050 | D21: =#REF! -> #REF! | E21: =#REF! -> #REF! | F21: =#REF! -> #REF! | G21: =#REF! -> #REF! | H21: =#REF! -> #REF! | I21: =#REF! -> #REF! | K21: Danzas Folkóricas Argentinas infantil | L21: Leandro N. Alem
A22: 21 | B22: Chales Gabriel Agustin | C22: 44431 | D22: Johanachales@gmail.com | F22: 41179 | G22: 9 | K22: Guitarra | L22: Leandro N. Alem | Z22: =COUNT(M22:X22) -> 0 | AA22: Lunes 18:30 hs | AB22: Guitarra
A23: 22 | B23: =#REF! -> #REF! | C23: 45053 | D23: =#REF! -> #REF! | E23: =#REF! -> #REF! | F23: =#REF! -> #REF! | G23: =#REF! -> #REF! | H23: =#REF! -> #REF! | I23: =#REF! -> #REF! | K23: =#REF! -> #REF! | L23: Leandro N. Alem
A24: 23 | B24: =#REF! -> #REF! | C24: 45054 | D24: =#REF! -> #REF! | E24: =#REF! -> #REF! | F24: =#REF! -> #REF! | G24: =#REF! -> #REF! | H24: =#REF! -> #REF! | I24: =#REF! -> #REF! | K24: =#REF! -> #REF! | L24: Leandro N. Alem
A25: 24 | B25: =#REF! -> #REF! | C25: 45073 | D25: =#REF! -> #REF! | E25: =#REF! -> #REF! | F25: =#REF! -> #REF! | G25: =#REF! -> #REF! | H25: =#REF! -> #REF! | I25: =#REF! -> #REF! | K25: =#REF! -> #REF! | L25: Leandro N. Alem
A26: 25 | B26: =#REF! -> #REF! | C26: 45072 | D26: =#REF! -> #REF! | E26: =#REF! -> #REF! | F26: =#REF! -> #REF! | G26: =#REF! -> #REF! | H26: =#REF! -> #REF! | I26: =#REF! -> #REF! | K26: =#REF! -> #REF! | L26: Leandro N. Alem
A27: 26 | B27: =#REF! -> #REF! | C27: 45069 | D27: =#REF! -> #REF! | E27: =#REF! -> #REF! | F27: =#REF! -> #REF! | G27: =#REF! -> #REF! | H27: =#REF! -> #REF! | I27: =#REF! -> #REF! | K27: =#REF! -> #REF! | L27: Leandro N. Alem
A28: 27 | B28: =#REF! -> #REF! | C28: 45066 | D28: =#REF! -> #REF! | E28: =#REF! -> #REF! | F28: =#REF! -> #REF! | G28: =#REF! -> #REF! | H28: =#REF! -> #REF! | I28: =#REF! -> #REF! | K28: =#REF! -> #REF! | L28: =#REF! -> #REF!
A29: 28 | B29: =#REF! -> #REF! | D29: =#REF! -> #REF! | E29: =#REF! -> #REF! | F29: =#REF! -> #REF! | G29: =#REF! -> #REF! | H29: =#REF! -> #REF! | I29: =#REF! -> #REF! | K29: =#REF! -> #REF! | L29: Leandro N. Alem
A30: 29 | B30: =#REF! -> #REF! | C30: 45063 | D30: =#REF! -> #REF! | E30: =#REF! -> #REF! | F30: =#REF! -> #REF! | G30: =#REF! -> #REF! | H30: =#REF! -> #REF! | I30: =#REF! -> #REF! | K30: =#REF! -> #REF! | L30: =#REF! -> #REF!
A31: 30 | B31: =#REF! -> #REF! | C31: 45058 | D31: =#REF! -> #REF! | E31: =#REF! -> #REF! | F31: =#REF! -> #REF! | G31: =#REF! -> #REF! | H31: =#REF! -> #REF! | I31: =#REF! -> #REF! | K31: =#REF! -> #REF! | L31: =#REF! -> #REF!
A32: 31 | B32: =#REF! -> #REF! | C32: 45074 | D32: =#REF! -> #REF! | E32: =#REF! -> #REF! | F32: =#REF! -> #REF! | G32: =#REF! -> #REF! | H32: =#REF! -> #REF! | I32: =#REF! -> #REF! | K32: Solo BAILAMOS | L32: Leandro N. Alem
A33: 32 | B33: =#REF! -> #REF! | C33: 45060 | D33: =#REF! -> #REF! | E33: =#REF! -> #REF! | F33: =#REF! -> #REF! | G33: =#REF! -> #REF! | H33: =#REF! -> #REF! | I33: =#REF! -> #REF! | K33: =#REF! -> #REF! | L33: =#REF! -> #REF!
A34: 33 | B34: =#REF! -> #REF! | D34: =#REF! -> #REF! | E34: =#REF! -> #REF! | F34: =#REF! -> #REF! | G34: =#REF! -> #REF! | H34: =#REF! -> #REF! | I34: =#REF! -> #REF! | K34: Solo BAILAMOS | L34: Leandro N. Alem
A35: 34 | B35: =#REF! -> #REF! | C35: 45059 | D35: =#REF! -> #REF! | E35: =#REF! -> #REF! | F35: =#REF! -> #REF! | G35: =#REF! -> #REF! | H35: =#REF! -> #REF! | I35: =#REF! -> #REF! | K35: =#REF! -> #REF! | L35: Leandro N. Alem
A36: 35 | B36: =#REF! -> #REF! | C36: 45061 | D36: =#REF! -> #REF! | E36: =#REF! -> #REF! | F36: =#REF! -> #REF! | G36: =#REF! -> #REF! | H36: =#REF! -> #REF! | I36: =#REF! -> #REF! | K36: =#REF! -> #REF! | L36: Leandro N. Alem
A37: 36 | B37: =#REF! -> #REF! | C37: 45068 | D37: =#REF! -> #REF! | E37: =#REF! -> #REF! | F37: =#REF! -> #REF! | G37: =#REF! -> #REF! | H37: =#REF! -> #REF! | I37: =#REF! -> #REF! | K37: =#REF! -> #REF! | L37: Leandro N. Alem
A38: 37 | B38: =#REF! -> #REF! | C38: 45064 | D38: =#REF! -> #REF! | E38: =#REF! -> #REF! | F38: =#REF! -> #REF! | G38: =#REF! -> #REF! | H38: =#REF! -> #REF! | I38: =#REF! -> #REF! | K38: =#REF! -> #REF! | L38: =#REF! -> #REF!
A39: 38 | B39: =#REF! -> #REF! | C39: 45071 | D39: =#REF! -> #REF! | E39: =#REF! -> #REF! | F39: =#REF! -> #REF! | G39: =#REF! -> #REF! | H39: =#REF! -> #REF! | I39: =#REF! -> #REF! | K39: =#REF! -> #REF! | L39: Leandro N. Alem
A40: 39 | B40: =#REF! -> #REF! | C40: 45070 | D40: =#REF! -> #REF! | E40: =#REF! -> #REF! | F40: =#REF! -> #REF! | G40: =#REF! -> #REF! | H40: =#REF! -> #REF! | I40: =#REF! -> #REF! | K40: =#REF! -> #REF! | L40: Leandro N. Alem
A41: 40 | B41: =#REF! -> #REF! | C41: 45065 | D41: =#REF! -> #REF! | E41: =#REF! -> #REF! | F41: =#REF! -> #REF! | G41: =#REF! -> #REF! | H41: =#REF! -> #REF! | I41: =#REF! -> #REF! | K41: =#REF! -> #REF! | L41: Leandro N. Alem
A42: 41 | B42: =#REF! -> #REF! | C42: 45062 | D42: =#REF! -> #REF! | E42: =#REF! -> #REF! | F42: =#REF! -> #REF! | G42: =#REF! -> #REF! | H42: =#REF! -> #REF! | I42: =#REF! -> #REF! | K42: =#REF! -> #REF! | L42: Leandro N. Alem
A43: 42 | B43: Cutti Chiara Jaqueline | D43: tizianakutti37@gmail.com | E43: 52808568 | F43: 41344 | H43: Manzana Nº 57 Calle 25 de Mayo | K43: Taller "Paisanitos" (3 a 5 años) | L43: Leandro N. Alem
A44: 43 | B44: Genecini Sayra Thaís | C44: 44776 | D44: slobogen64@gmail.com | E44: 57730729 | F44: 43598 | G44: 3 | H44: Gobernador López | I44: 3755448187 | K44: Taller "Paisanitos" (3 a 5 años) | L44: Gobernador López
A45: 44 | B45: =#REF! -> #REF! | C45: 45052 | D45: =#REF! -> #REF! | E45: =#REF! -> #REF! | F45: =#REF! -> #REF! | G45: =#REF! -> #REF! | H45: =#REF! -> #REF! | I45: =#REF! -> #REF! | K45: Taller "Paisanitos" (3 a 5 años) | L45: Leandro N. Alem
A46: 45 | B46: Magalí De Simón | C46: 44981.435 | D46: esena006@gmail.com | E46: 56159058 | F46: 42857 | G46: 5 | H46: Barrio Alem 1 casa 8 | I46: 3754470114 | K46: Taller "Paisanitos" (3 a 5 años) | L46: Leandro N. Alem
A47: 46 | B47: Marquez Bastian Lorenzo | C47: 44780 | D47: leonelasolbaez@hotmail.com | E47: 57851937 | F47: 43717 | G47: 3 | H47: Loteo Bella Vista, Mzna K1- Lote 6 | I47: 3754451590 | K47: Taller "Paisanitos" (3 a 5 años) | L47: Leandro N. Alem
A48: 47 | B48: Mia francesca maximowicz | C48: 44982 | D48: gabrielagrave4@gmail.com | E48: 56170549 | F48: 43441 | G48: 4 | H48: Belgrano 1595 | I48: 3754406713 | K48: Taller "Paisanitos" (3 a 5 años) | L48: Leandro N. Alem
A49: 48 | B49: Nitsch Martínez Hinata Sofia | C49: 44779 | D49: romiisol014@gmail.com | E49: 56025195 | F49: 42744 | G49: 5 | H49: Barrio Perón casa 2 | I49: 3754417691 | K49: Taller "Paisanitos" (3 a 5 años) | L49: Leandro N. Alem | AA49: Miercoles de 17:00 - 18:00 hs | AB49: Primero Preparatorio
A50: 49 | B50: Olivera Camila Belén | C50: 44635 | D50: centroesteticoalmabella@gmail.com | F50: 43705 | G50: 2 | H50: Saavedra 112 | I50: 3754436602 | K50: Taller "Paisanitos" (3 a 5 años) | L50: Leandro N. Alem
A51: 50 | B51: =#REF! -> #REF! | C51: 45067 | D51: =#REF! -> #REF! | E51: =#REF! -> #REF! | F51: =#REF! -> #REF! | G51: =#REF! -> #REF! | H51: =#REF! -> #REF! | I51: =#REF! -> #REF! | K51: =#REF! -> #REF! | L51: Leandro N. Alem
A52: 51 | B52: Paniagua Julieta Luján | C52: 44635 | D52: carlaasuncion@hotmail.com.ar | E52: 56079104 | F52: 43185 | G52: 4 | H52: Saavedra 112 | I52: 3754436602 | K52: Taller "Paisanitos" (3 a 5 años) | L52: Leandro N. Alem
A53: 52 | B53: Candia Sabrina | C53: 44602 | D53: normarendich25@gmail.com | E53: 52173063 | F53: 41269 | G53: 9 | H53: Itacaruare | I53: 3754436329 | K53: Taller de iniciación Danzas Folkloricas Argentinas | L53: Itacaruaré
A54: 53 | B54: Gomez Valentina Aylen | C54: 44602 | D54: sosaalondra808@gmail.com | E54: 53588595 | F54: 41543 | G54: 8 | H54: Itacaruare | I54: 3754534016 | K54: Taller de iniciación Danzas Folkloricas Argentinas | L54: Itacaruaré
A55: 54 | B55: Rizzello Alma Mia | C55: 44223 | D55: dgerardor@hotmail.com | E55: 53818991 | G55: 8 | H55: lote 621 paraje las mandarinas | K55: Taller de iniciación Danzas Folkloricas Argentinas | L55: Itacaruaré
A56: 55 | B56: Rizzello Valentina Aylen | C56: 44223 | D56: dgerardor@hotmail.com | E56: 55343203 | G56: 5 | H56: lote 621 paraje las mandarinas | K56: Taller de iniciación Danzas Folkloricas Argentinas | L56: Itacaruaré
A57: 56 | B57: Rodriguez Dos Santos Milagros Ludmila | C57: 44223 | D57: Noeliads14@gmail.com | E57: 53963419 | F57: 42262 | G57: 7 | H57: Barrio 30 viv Jose Carlos Freaza casa 12 | I57: 3754416242 | K57: Taller de iniciación Danzas Folkloricas Argentinas | L57: Itacaruaré
A58: 57 | B58: Suárez Alejandro Gastón | C58: 44223 | D58: barbaracontreras758@gmail.com | E58: 49474679 | F58: 40899 | G58: 10 | H58: Itacaruare | I58: 3754431451 | K58: Taller de iniciación Danzas Folkloricas Argentinas | L58: Itacaruaré
A59: 58 | B59: =#REF! -> #REF! | C59: 44224 | D59: =#REF! -> #REF! | E59: =#REF! -> #REF! | G59: =#REF! -> #REF! | H59: =#REF! -> #REF! | I59: =#REF! -> #REF! | K59: Taller de Tejido
A60: 59 | B60: =#REF! -> #REF! | C60: 44225 | D60: =#REF! -> #REF! | E60: =#REF! -> #REF! | G60: =#REF! -> #REF! | H60: =#REF! -> #REF! | I60: =#REF! -> #REF! | K60: Taller de Tejido | L60: Leandro N. Alem
A61: 60 | B61: Gianna victoria viera troil | C61: 45317.679 | D61: Luchagana1@gmail.com | E61: 56719844 | G61: 6 | H61: Astrada 508 | I61: 3754401018 | K61: Manualidades para niños | L61: Leandro N. Alem
A62: 61 | B62: Luana sherlyn viera troil | C62: 45317.683 | D62: Luchagana1@gmail.com | E62: 56637457 | G62: 9 | H62: Astrada 508 | I62: 3754401018 | K62: Manualidades para niños | L62: Leandro N. Alem
A63: 62 | B63: Caarolina Ines Gomez | C63: 45319.479 | D63: carogo12mez3@gmail.com | E63: 40410777 | G63: 26 | H63: Calle córdoba 519, Leandro N Alem | I63: 3754495541 | K63: Corte y confección | L63: Leandro N. Alem
A64: 63 | B64: Veronica galarza | C64: 45319.546 | D64: Veronicagalarza705@gmail.com | E64: 36470561 | G64: 30 | H64: Calle el paraiso lote1 mz R | I64: 3754525043 | K64: Corte y confección | L64: Leandro N. Alem
A65: 64 | B65: Dana milagros Diaz Martin | C65: 45321.375 | D65: mbareteviajesevt@gmail.com | E65: 48889747 | G65: 15 | H65: Corrientes 139 Leandro N Alem | I65: 3754528106 | K65: Canto | L65: Leandro N. Alem
A66: 65 | B66: Sofía Milagros Benchaski | C66: 45318.458 | D66: maidanalauraedith@gmail.com | E66: 54945841 | F66: 42243 | G66: 8 | H66: Av San Martin 589 | I66: 3758440666 | K66: Taller "folklore un lenguaje artístico" (Desde 6 años) | L66: Leandro N. Alem
A67: 66 | B67: Emma Valentina Guazzi | C67: 45319 | D67: guazzitizziano@gmail.com | E67: 53790456 | G67: 9 | H67: Bº Virgen del Rosario | I67: 3704-810796 | K67: Manualidades para niños | L67: Leandro N. Alem
A68: 67 | B68: Maciel Kreischer Victoria | C68: 44989 | D68: javieromaciel@gmail.com | E68: 57607912 | F68: 2504/2019 | G68: 4 | H68: Calcuta 282 | I68: 3754478360 | K68: =#REF! -> #REF! | L68: Leandro N. Alem
A69: 68 | B69: Nahyara Luján Radaelli | C69: 44990 | D69: pamela.chaihort@gmail.com | E69: 57145256 | F69: 43362 | G69: 5 | H69: Cañafistola 215 Alem | I69: 3754416012 | K69: Taller "Paisanitos" (3 a 5 años) | L69: Leandro N. Alem
A70: 69 | B70: Aylen Elizabeth Sosa | C70: 44991 | D70: natiflu77@gmail.com | E70: 52309305 | F70: 41200 | G70: 11 | H70: Itacaruare | I70: 3754491842 | K70: Danzas Folkloricas Argentinas (infantiles) | L70: Itacaruaré
A71: 70 | B71: Pufal Mariana Elizabeth | C71: 45386 | D71: marianaepufal@gmail.com | E71: 28539165 | F71: 29736 | G71: 42 | H71: Bo Janssen Mz 1 Lote 4 | I71: 3754416418 | K71: Solo bailamos Adultos | L71: Leandro N. Alem | N71: 4000 | P71: 6000
A72: 71 | B72: Carballo Leonardo Sebastian | C72: 45386 | D72: leonardosebastiancarballo@gmail.com | E72: 41851970 | F72: 36256 | G72: 25 | H72: Mayordomo Olivera 1196 | I72: 3754456062 | K72: Solo bailamos Adultos | L72: Leandro N. Alem | N72: 4000 | P72: 6000
A73: 72 | B73: Koch Brenda | D73: mariana.metner@gmail.com | K73: =#REF! -> #REF! | L73: Leandro N. Alem | N73: 4000 | P73: 6000
A74: 73 | B74: Juan Maximiliano Damian | D74: damianjuanmaximiliano@gmail.com
A75: 5 | B75: Roballo Antonela Itatí | C75: 10/30/2020 | D75: roballoantonela@gmail.com | E75: 41506733 | F75: 36017 | G75: 22 | H75: Paraje La Corita | I75: 3754430914 | J75: Docente | K75: Danzas Folkóricas Argentinas "Modalidad Acelerado" | L75: Santa María | N75: 5000 | Z75: =COUNT(M75:X75) -> 1 | AA75: Sábados de 08:00 - 12:00 hs | AB75: Primero Preparatorio

Sheet Examen
A1: =IFERROR(__xludf.DUMMYFUNCTION("IMPORTRANGE(""https://docs.google.com/spreadsheets/d/1h8i0mY2i70DSX-Sju4sC8Pudz_Rdlib8tF5tFWnSGdA"",""Respuestas!A:h"")"),"Marca temporal") -> Marca temporal | B1: =IFERROR(__xludf.DUMMYFUNCTION("""COMPUTED_VALUE"""),"Apellido y Nombre (cómo aparece en el DNI)") -> Apellido y Nombre (cómo aparece en el DNI) | C1: =IFERROR(__xludf.DUMMYFUNCTION("""COMPUTED_VALUE"""),"DNI") -> DNI | D1: =IFERROR(__xludf.DUMMYFUNCTION("""COMPUTED_VALUE"""),"Edad") -> Edad | E1: =IFERROR(__xludf.DUMMYFUNCTION("""COMPUTED_VALUE"""),"Sede a la que pertenece") -> Sede a la que pertenece | F1: =IFERROR(__xludf.DUMMYFUNCTION("""COMPUTED_VALUE"""),"Nivel que rinde [Preparatorio]") -> Nivel que rinde [Preparatorio] | G1: =IFERROR(__xludf.DUMMYFUNCTION("""COMPUTED_VALUE"""),"Nivel que rinde [Elemental]") -> Nivel que rinde [Elemental] | H1: =IFERROR(__xludf.DUMMYFUNCTION("""COMPUTED_VALUE"""),"Nivel que rinde [Superior]") -> Nivel que rinde [Superior]
A2: =IFERROR(__xludf.DUMMYFUNCTION("""COMPUTED_VALUE"""),45944.83512452546) -> 45944.835 | B2: =IFERROR(__xludf.DUMMYFUNCTION("""COMPUTED_VALUE"""),"Back Brenda Anahi ") -> Back Brenda Anahi | C2: =IFERROR(__xludf.DUMMYFUNCTION("""COMPUTED_VALUE"""),"52739073") -> 52739073 | D2: =IFERROR(__xludf.DUMMYFUNCTION("""COMPUTED_VALUE"""),12.0) -> 12 | E2: =IFERROR(__xludf.DUMMYFUNCTION("""COMPUTED_VALUE"""),"Alem") -> Alem | F2: =IFERROR(__xludf.DUMMYFUNCTION("""COMPUTED_VALUE"""),"Segundo") -> Segundo
A3: =IFERROR(__xludf.DUMMYFUNCTION("""COMPUTED_VALUE"""),45944.32252431713) -> 45944.323 | B3: =IFERROR(__xludf.DUMMYFUNCTION("""COMPUTED_VALUE"""),"Carolina Belén Rominski ") -> Carolina Belén Rominski | C3: =IFERROR(__xludf.DUMMYFUNCTION("""COMPUTED_VALUE"""),"43831994") -> 43831994 | D3: =IFERROR(__xludf.DUMMYFUNCTION("""COMPUTED_VALUE"""),23.0) -> 23 | E3: =IFERROR(__xludf.DUMMYFUNCTION("""COMPUTED_VALUE"""),"Alem") -> Alem | F3: =IFERROR(__xludf.DUMMYFUNCTION("""COMPUTED_VALUE"""),"Segundo") -> Segundo
A4: =IFERROR(__xludf.DUMMYFUNCTION("""COMPUTED_VALUE"""),45946.65316971065) -> 45946.653 | B4: =IFERROR(__xludf.DUMMYFUNCTION("""COMPUTED_VALUE"""),"Hanna Denise Machado") -> Hanna Denise Machado | C4: =IFERROR(__xludf.DUMMYFUNCTION("""COMPUTED_VALUE"""),"52809887") -> 52809887 | D4: =IFERROR(__xludf.DUMMYFUNCTION("""COMPUTED_VALUE"""),12.0) -> 12 | E4: =IFERROR(__xludf.DUMMYFUNCTION("""COMPUTED_VALUE"""),"Alem") -> Alem | F4: =IFERROR(__xludf.DUMMYFUNCTION("""COMPUTED_VALUE"""),"Segundo") -> Segundo
A5: =IFERROR(__xludf.DUMMYFUNCTION("""COMPUTED_VALUE"""),45944.78662118055) -> 45944.787 | B5: =IFERROR(__xludf.DUMMYFUNCTION("""COMPUTED_VALUE"""),"Pufal Mariana Elizabeth ") -> Pufal Mariana Elizabeth | C5: =IFERROR(__xludf.DUMMYFUNCTION("""COMPUTED_VALUE"""),"28539165") -> 28539165 | D5: =IFERROR(__xludf.DUMMYFUNCTION("""COMPUTED_VALUE"""),44.0) -> 44 | E5: =IFERROR(__xludf.DUMMYFUNCTION("""COMPUTED_VALUE"""),"Alem") -> Alem | F5: =IFERROR(__xludf.DUMMYFUNCTION("""COMPUTED_VALUE"""),"Segundo") -> Segundo
A6: =IFERROR(__xludf.DUMMYFUNCTION("""COMPUTED_VALUE"""),45944.32984788195) -> 45944.33 | B6: =IFERROR(__xludf.DUMMYFUNCTION("""COMPUTED_VALUE"""),"Wach Candela Jazmín ") -> Wach Candela Jazmín | C6: =IFERROR(__xludf.DUMMYFUNCTION("""COMPUTED_VALUE"""),"53090248") -> 53090248 | D6: =IFERROR(__xludf.DUMMYFUNCTION("""COMPUTED_VALUE"""),12.0) -> 12 | E6: =IFERROR(__xludf.DUMMYFUNCTION("""COMPUTED_VALUE"""),"Alem") -> Alem | F6: =IFERROR(__xludf.DUMMYFUNCTION("""COMPUTED_VALUE"""),"Segundo") -> Segundo
A7: =IFERROR(__xludf.DUMMYFUNCTION("""COMPUTED_VALUE"""),45944.93285814815) -> 45944.933 | B7: =IFERROR(__xludf.DUMMYFUNCTION("""COMPUTED_VALUE"""),"Benjamin Maximiliano Losanto") -> Benjamin Maximiliano Losanto | C7: =IFERROR(__xludf.DUMMYFUNCTION("""COMPUTED_VALUE"""),"53796732") -> 53796732 | D7: =IFERROR(__xludf.DUMMYFUNCTION("""COMPUTED_VALUE"""),11.0) -> 11 | E7: =IFERROR(__xludf.DUMMYFUNCTION("""COMPUTED_VALUE"""),"Alem") -> Alem | G7: =IFERROR(__xludf.DUMMYFUNCTION("""COMPUTED_VALUE"""),"Segundo") -> Segundo
A8: =IFERROR(__xludf.DUMMYFUNCTION("""COMPUTED_VALUE"""),45947.656347094904) -> 45947.656 | B8: =IFERROR(__xludf.DUMMYFUNCTION("""COMPUTED_VALUE"""),"Leites Franco Emmanuel ") -> Leites Franco Emmanuel | C8: =IFERROR(__xludf.DUMMYFUNCTION("""COMPUTED_VALUE"""),"34234803 ") -> 34234803 | D8: =IFERROR(__xludf.DUMMYFUNCTION("""COMPUTED_VALUE"""),31.0) -> 31 | E8: =IFERROR(__xludf.DUMMYFUNCTION("""COMPUTED_VALUE"""),"Alem") -> Alem | G8: =IFERROR(__xludf.DUMMYFUNCTION("""COMPUTED_VALUE"""),"Primero") -> Primero
A9: =IFERROR(__xludf.DUMMYFUNCTION("""COMPUTED_VALUE"""),45947.656347094904) -> 45947.656 | B9: =IFERROR(__xludf.DUMMYFUNCTION("""COMPUTED_VALUE"""),"Leites Franco Emmanuel ") -> Leites Franco Emmanuel | C9: =IFERROR(__xludf.DUMMYFUNCTION("""COMPUTED_VALUE"""),"34234803 ") -> 34234803 | D9: =IFERROR(__xludf.DUMMYFUNCTION("""COMPUTED_VALUE"""),31.0) -> 31 | E9: =IFERROR(__xludf.DUMMYFUNCTION("""COMPUTED_VALUE"""),"Alem") -> Alem | G9: =IFERROR(__xludf.DUMMYFUNCTION("""COMPUTED_VALUE"""),"Segundo") -> Segundo
A10: =IFERROR(__xludf.DUMMYFUNCTION("""COMPUTED_VALUE"""),45948.94379193287) -> 45948.944 | B10: =IFERROR(__xludf.DUMMYFUNCTION("""COMPUTED_VALUE"""),"Luz Milagros Pona Romero ") -> Luz Milagros Pona Romero | C10: =IFERROR(__xludf.DUMMYFUNCTION("""COMPUTED_VALUE"""),"53536539") -> 53536539 | D10: =IFERROR(__xludf.DUMMYFUNCTION("""COMPUTED_VALUE"""),11.0) -> 11 | E10: =IFERROR(__xludf.DUMMYFUNCTION("""COMPUTED_VALUE"""),"Alem") -> Alem | G10: =IFERROR(__xludf.DUMMYFUNCTION("""COMPUTED_VALUE"""),"Segundo") -> Segundo
A11: =IFERROR(__xludf.DUMMYFUNCTION("""COMPUTED_VALUE"""),45945.50250314815) -> 45945.503 | B11: =IFERROR(__xludf.DUMMYFUNCTION("""COMPUTED_VALUE"""),"Olexen Mariana Cinthia ") -> Olexen Mariana Cinthia | C11: =IFERROR(__xludf.DUMMYFUNCTION("""COMPUTED_VALUE"""),"42288209") -> 42288209 | D11: =IFERROR(__xludf.DUMMYFUNCTION("""COMPUTED_VALUE"""),25.0) -> 25 | E11: =IFERROR(__xludf.DUMMYFUNCTION("""COMPUTED_VALUE"""),"Alem") -> Alem | F11: =IFERROR(__xludf.DUMMYFUNCTION("""COMPUTED_VALUE"""),"Primero") -> Primero
A12: =IFERROR(__xludf.DUMMYFUNCTION("""COMPUTED_VALUE"""),45944.33147420139) -> 45944.331 | B12: =IFERROR(__xludf.DUMMYFUNCTION("""COMPUTED_VALUE"""),"Roballo Antonela Itatí ") -> Roballo Antonela Itatí | C12: =IFERROR(__xludf.DUMMYFUNCTION("""COMPUTED_VALUE"""),"41506733") -> 41506733 | D12: =IFERROR(__xludf.DUMMYFUNCTION("""COMPUTED_VALUE"""),27.0) -> 27 | E12: =IFERROR(__xludf.DUMMYFUNCTION("""COMPUTED_VALUE"""),"Alem") -> Alem | H12: =IFERROR(__xludf.DUMMYFUNCTION("""COMPUTED_VALUE"""),"Diploma") -> Diploma
A13: =IFERROR(__xludf.DUMMYFUNCTION("""COMPUTED_VALUE"""),45944.91907858796) -> 45944.919 | B13: =IFERROR(__xludf.DUMMYFUNCTION("""COMPUTED_VALUE"""),"Tereschuk Anibal Adrian") -> Tereschuk Anibal Adrian | C13: =IFERROR(__xludf.DUMMYFUNCTION("""COMPUTED_VALUE"""),"40197439") -> 40197439 | D13: =IFERROR(__xludf.DUMMYFUNCTION("""COMPUTED_VALUE"""),28.0) -> 28 | E13: =IFERROR(__xludf.DUMMYFUNCTION("""COMPUTED_VALUE"""),"Alem") -> Alem | F13: =IFERROR(__xludf.DUMMYFUNCTION("""COMPUTED_VALUE"""),"Primero") -> Primero
A14: =IFERROR(__xludf.DUMMYFUNCTION("""COMPUTED_VALUE"""),45947.72061549769) -> 45947.721 | B14: =IFERROR(__xludf.DUMMYFUNCTION("""COMPUTED_VALUE"""),"Yasmin Araceli Cerdan") -> Yasmin Araceli Cerdan | C14: =IFERROR(__xludf.DUMMYFUNCTION("""COMPUTED_VALUE"""),"53092552") -> 53092552 | D14: =IFERROR(__xludf.DUMMYFUNCTION("""COMPUTED_VALUE"""),12.0) -> 12 | E14: =IFERROR(__xludf.DUMMYFUNCTION("""COMPUTED_VALUE"""),"Alem") -> Alem | G14: =IFERROR(__xludf.DUMMYFUNCTION("""COMPUTED_VALUE"""),"Segundo") -> Segundo
A15: =IFERROR(__xludf.DUMMYFUNCTION("""COMPUTED_VALUE"""),45979.33452512731) -> 45979.335 | B15: =IFERROR(__xludf.DUMMYFUNCTION("""COMPUTED_VALUE"""),"Arndt Ona Guillermina") -> Arndt Ona Guillermina | C15: =IFERROR(__xludf.DUMMYFUNCTION("""COMPUTED_VALUE"""),"53785780") -> 53785780 | D15: =IFERROR(__xludf.DUMMYFUNCTION("""COMPUTED_VALUE"""),11.0) -> 11 | E15: =IFERROR(__xludf.DUMMYFUNCTION("""COMPUTED_VALUE"""),"Alem") -> Alem | F15: =IFERROR(__xludf.DUMMYFUNCTION("""COMPUTED_VALUE"""),"Segundo") -> Segundo
A16: =IFERROR(__xludf.DUMMYFUNCTION("""COMPUTED_VALUE"""),45979.3965162963) -> 45979.397 | B16: =IFERROR(__xludf.DUMMYFUNCTION("""COMPUTED_VALUE"""),"Frenna Zoe Alexia") -> Frenna Zoe Alexia | C16: =IFERROR(__xludf.DUMMYFUNCTION("""COMPUTED_VALUE"""),"53785766") -> 53785766 | D16: =IFERROR(__xludf.DUMMYFUNCTION("""COMPUTED_VALUE"""),11.0) -> 11 | E16: =IFERROR(__xludf.DUMMYFUNCTION("""COMPUTED_VALUE"""),"Alem") -> Alem | F16: =IFERROR(__xludf.DUMMYFUNCTION("""COMPUTED_VALUE"""),"Segundo") -> Segundo
A17: =IFERROR(__xludf.DUMMYFUNCTION("""COMPUTED_VALUE"""),45947.662856423616) -> 45947.663 | B17: =IFERROR(__xludf.DUMMYFUNCTION("""COMPUTED_VALUE"""),"Aguirre Guadalupe Xiomara ") -> Aguirre Guadalupe Xiomara | C17: =IFERROR(__xludf.DUMMYFUNCTION("""COMPUTED_VALUE"""),"55617160") -> 55617160 | D17: =IFERROR(__xludf.DUMMYFUNCTION("""COMPUTED_VALUE"""),9.0) -> 9 | E17: =IFERROR(__xludf.DUMMYFUNCTION("""COMPUTED_VALUE"""),"Arroyo del Medio") -> Arroyo del Medio | F17: =IFERROR(__xludf.DUMMYFUNCTION("""COMPUTED_VALUE"""),"Primero") -> Primero
A18: =IFERROR(__xludf.DUMMYFUNCTION("""COMPUTED_VALUE"""),45947.66467428241) -> 45947.665 | B18: =IFERROR(__xludf.DUMMYFUNCTION("""COMPUTED_VALUE"""),"Gimena Aylin Leites ") -> Gimena Aylin Leites | C18: =IFERROR(__xludf.DUMMYFUNCTION("""COMPUTED_VALUE"""),"54232826") -> 54232826 | D18: =IFERROR(__xludf.DUMMYFUNCTION("""COMPUTED_VALUE"""),10.0) -> 10 | E18: =IFERROR(__xludf.DUMMYFUNCTION("""COMPUTED_VALUE"""),"Arroyo del Medio") -> Arroyo del Medio | F18: =IFERROR(__xludf.DUMMYFUNCTION("""COMPUTED_VALUE"""),"Primero") -> Primero
A19: =IFERROR(__xludf.DUMMYFUNCTION("""COMPUTED_VALUE"""),45951.397326342594) -> 45951.397 | B19: =IFERROR(__xludf.DUMMYFUNCTION("""COMPUTED_VALUE"""),"Araujo Mariza Itatí ") -> Araujo Mariza Itatí | C19: =IFERROR(__xludf.DUMMYFUNCTION("""COMPUTED_VALUE"""),"36456529") -> 36456529 | D19: =IFERROR(__xludf.DUMMYFUNCTION("""COMPUTED_VALUE"""),32.0) -> 32 | E19: =IFERROR(__xludf.DUMMYFUNCTION("""COMPUTED_VALUE"""),"Cerro Azul") -> Cerro Azul | F19: =IFERROR(__xludf.DUMMYFUNCTION("""COMPUTED_VALUE"""),"Primero") -> Primero
A20: =IFERROR(__xludf.DUMMYFUNCTION("""COMPUTED_VALUE"""),45947.661569375) -> 45947.662 | B20: =IFERROR(__xludf.DUMMYFUNCTION("""COMPUTED_VALUE"""),"Báez Natali Yaquelin") -> Báez Natali Yaquelin | C20: =IFERROR(__xludf.DUMMYFUNCTION("""COMPUTED_VALUE"""),"43331812") -> 43331812 | D20: =IFERROR(__xludf.DUMMYFUNCTION("""COMPUTED_VALUE"""),24.0) -> 24 | E20: =IFERROR(__xludf.DUMMYFUNCTION("""COMPUTED_VALUE"""),"Cerro Azul") -> Cerro Azul | F20: =IFERROR(__xludf.DUMMYFUNCTION("""COMPUTED_VALUE"""),"Primero") -> Primero
A21: =IFERROR(__xludf.DUMMYFUNCTION("""COMPUTED_VALUE"""),45947.68593521991) -> 45947.686 | B21: =IFERROR(__xludf.DUMMYFUNCTION("""COMPUTED_VALUE"""),"Ferreyra Yesica Belén ") -> Ferreyra Yesica Belén | C21: =IFERROR(__xludf.DUMMYFUNCTION("""COMPUTED_VALUE"""),"36456601") -> 36456601 | D21: =IFERROR(__xludf.DUMMYFUNCTION("""COMPUTED_VALUE"""),32.0) -> 32 | E21: =IFERROR(__xludf.DUMMYFUNCTION("""COMPUTED_VALUE"""),"Cerro Azul") -> Cerro Azul | F21: =IFERROR(__xludf.DUMMYFUNCTION("""COMPUTED_VALUE"""),"Primero") -> Primero
A22: =IFERROR(__xludf.DUMMYFUNCTION("""COMPUTED_VALUE"""),45951.38710287037) -> 45951.387 | B22: =IFERROR(__xludf.DUMMYFUNCTION("""COMPUTED_VALUE"""),"Francesconi Agustina Nazarena ") -> Francesconi Agustina Nazarena | C22: =IFERROR(__xludf.DUMMYFUNCTION("""COMPUTED_VALUE"""),"42515020 ") -> 42515020 | D22: =IFERROR(__xludf.DUMMYFUNCTION("""COMPUTED_VALUE"""),25.0) -> 25 | E22: =IFERROR(__xludf.DUMMYFUNCTION("""COMPUTED_VALUE"""),"Cerro Azul") -> Cerro Azul | F22: =IFERROR(__xludf.DUMMYFUNCTION("""COMPUTED_VALUE"""),"Primero") -> Primero
A23: =IFERROR(__xludf.DUMMYFUNCTION("""COMPUTED_VALUE"""),45944.552513449074) -> 45944.553 | B23: =IFERROR(__xludf.DUMMYFUNCTION("""COMPUTED_VALUE"""),"Cardozo Gómez Fernández Sofía itati") -> Cardozo Gómez Fernández Sofía itati | C23: =IFERROR(__xludf.DUMMYFUNCTION("""COMPUTED_VALUE"""),"53537483") -> 53537483 | D23: =IFERROR(__xludf.DUMMYFUNCTION("""COMPUTED_VALUE"""),11.0) -> 11 | E23: =IFERROR(__xludf.DUMMYFUNCTION("""COMPUTED_VALUE"""),"Itacaruaré") -> Itacaruaré | F23: =IFERROR(__xludf.DUMMYFUNCTION("""COMPUTED_VALUE"""),"Primero") -> Primero
A24: =IFERROR(__xludf.DUMMYFUNCTION("""COMPUTED_VALUE"""),45947.76365172454) -> 45947.764 | B24: =IFERROR(__xludf.DUMMYFUNCTION("""COMPUTED_VALUE"""),"Kohl de Oliveira William ") -> Kohl de Oliveira William | C24: =IFERROR(__xludf.DUMMYFUNCTION("""COMPUTED_VALUE"""),"53785767") -> 53785767 | D24: =IFERROR(__xludf.DUMMYFUNCTION("""COMPUTED_VALUE"""),11.0) -> 11 | E24: =IFERROR(__xludf.DUMMYFUNCTION("""COMPUTED_VALUE"""),"Itacaruaré") -> Itacaruaré | F24: =IFERROR(__xludf.DUMMYFUNCTION("""COMPUTED_VALUE"""),"Primero") -> Primero
A25: =IFERROR(__xludf.DUMMYFUNCTION("""COMPUTED_VALUE"""),45947.741382314816) -> 45947.741 | B25: =IFERROR(__xludf.DUMMYFUNCTION("""COMPUTED_VALUE"""),"Medina Candela Lissel Oraide ") -> Medina Candela Lissel Oraide | C25: =IFERROR(__xludf.DUMMYFUNCTION("""COMPUTED_VALUE"""),"55777016 ") -> 55777016 | D25: =IFERROR(__xludf.DUMMYFUNCTION("""COMPUTED_VALUE"""),9.0) -> 9 | E25: =IFERROR(__xludf.DUMMYFUNCTION("""COMPUTED_VALUE"""),"Itacaruaré") -> Itacaruaré | F25: =IFERROR(__xludf.DUMMYFUNCTION("""COMPUTED_VALUE"""),"Primero") -> Primero
A26: =IFERROR(__xludf.DUMMYFUNCTION("""COMPUTED_VALUE"""),45950.38479863426) -> 45950.385 | B26: =IFERROR(__xludf.DUMMYFUNCTION("""COMPUTED_VALUE"""),"Pawluk Ghisleyne Mariel") -> Pawluk Ghisleyne Mariel | C26: =IFERROR(__xludf.DUMMYFUNCTION("""COMPUTED_VALUE"""),"55488299") -> 55488299 | D26: =IFERROR(__xludf.DUMMYFUNCTION("""COMPUTED_VALUE"""),9.0) -> 9 | E26: =IFERROR(__xludf.DUMMYFUNCTION("""COMPUTED_VALUE"""),"Itacaruaré") -> Itacaruaré | F26: =IFERROR(__xludf.DUMMYFUNCTION("""COMPUTED_VALUE"""),"Primero") -> Primero
A27: =IFERROR(__xludf.DUMMYFUNCTION("""COMPUTED_VALUE"""),45944.53577581019) -> 45944.536 | B27: =IFERROR(__xludf.DUMMYFUNCTION("""COMPUTED_VALUE"""),"Roballo Florencia Agustina") -> Roballo Florencia Agustina | C27: =IFERROR(__xludf.DUMMYFUNCTION("""COMPUTED_VALUE"""),"55777006") -> 55777006 | D27: =IFERROR(__xludf.DUMMYFUNCTION("""COMPUTED_VALUE"""),9.0) -> 9 | E27: =IFERROR(__xludf.DUMMYFUNCTION("""COMPUTED_VALUE"""),"Itacaruaré") -> Itacaruaré | F27: =IFERROR(__xludf.DUMMYFUNCTION("""COMPUTED_VALUE"""),"Primero") -> Primero
A28: =IFERROR(__xludf.DUMMYFUNCTION("""COMPUTED_VALUE"""),45944.48489047454) -> 45944.485 | B28: =IFERROR(__xludf.DUMMYFUNCTION("""COMPUTED_VALUE"""),"Rodríguez Sofia Itatí") -> Rodríguez Sofia Itatí | C28: =IFERROR(__xludf.DUMMYFUNCTION("""COMPUTED_VALUE"""),"53963778") -> 53963778 | D28: =IFERROR(__xludf.DUMMYFUNCTION("""COMPUTED_VALUE"""),9.0) -> 9 | E28: =IFERROR(__xludf.DUMMYFUNCTION("""COMPUTED_VALUE"""),"Itacaruaré") -> Itacaruaré | F28: =IFERROR(__xludf.DUMMYFUNCTION("""COMPUTED_VALUE"""),"Primero") -> Primero
A29: =IFERROR(__xludf.DUMMYFUNCTION("""COMPUTED_VALUE"""),45944.366519884265) -> 45944.367 | B29: =IFERROR(__xludf.DUMMYFUNCTION("""COMPUTED_VALUE"""),"Da Rosa Luz Morena ") -> Da Rosa Luz Morena | C29: =IFERROR(__xludf.DUMMYFUNCTION("""COMPUTED_VALUE"""),"52300816") -> 52300816 | D29: =IFERROR(__xludf.DUMMYFUNCTION("""COMPUTED_VALUE"""),13.0) -> 13 | E29: =IFERROR(__xludf.DUMMYFUNCTION("""COMPUTED_VALUE"""),"Itacaruaré") -> Itacaruaré | F29: =IFERROR(__xludf.DUMMYFUNCTION("""COMPUTED_VALUE"""),"Segundo") -> Segundo
A30: =IFERROR(__xludf.DUMMYFUNCTION("""COMPUTED_VALUE"""),45947.71577708333) -> 45947.716 | B30: =IFERROR(__xludf.DUMMYFUNCTION("""COMPUTED_VALUE"""),"Rodriguez Ludmara Gisahi ") -> Rodriguez Ludmara Gisahi | C30: =IFERROR(__xludf.DUMMYFUNCTION("""COMPUTED_VALUE"""),"51083733") -> 51083733 | D30: =IFERROR(__xludf.DUMMYFUNCTION("""COMPUTED_VALUE"""),14.0) -> 14 | E30: =IFERROR(__xludf.DUMMYFUNCTION("""COMPUTED_VALUE"""),"Itacaruaré") -> Itacaruaré | F30: =IFERROR(__xludf.DUMMYFUNCTION("""COMPUTED_VALUE"""),"Segundo") -> Segundo
A31: =IFERROR(__xludf.DUMMYFUNCTION("""COMPUTED_VALUE"""),45948.463588645835) -> 45948.464 | B31: =IFERROR(__xludf.DUMMYFUNCTION("""COMPUTED_VALUE"""),"Candia Sabrina Yazmin ") -> Candia Sabrina Yazmin | C31: =IFERROR(__xludf.DUMMYFUNCTION("""COMPUTED_VALUE"""),"52173063") -> 52173063 | D31: =IFERROR(__xludf.DUMMYFUNCTION("""COMPUTED_VALUE"""),13.0) -> 13 | E31: =IFERROR(__xludf.DUMMYFUNCTION("""COMPUTED_VALUE"""),"Itacaruaré") -> Itacaruaré | G31: =IFERROR(__xludf.DUMMYFUNCTION("""COMPUTED_VALUE"""),"Primero") -> Primero
A32: =IFERROR(__xludf.DUMMYFUNCTION("""COMPUTED_VALUE"""),45947.715852291665) -> 45947.716 | B32: =IFERROR(__xludf.DUMMYFUNCTION("""COMPUTED_VALUE"""),"Cavallo Ámbar Abril") -> Cavallo Ámbar Abril | C32: =IFERROR(__xludf.DUMMYFUNCTION("""COMPUTED_VALUE"""),"52449851") -> 52449851 | D32: =IFERROR(__xludf.DUMMYFUNCTION("""COMPUTED_VALUE"""),13.0) -> 13 | E32: =IFERROR(__xludf.DUMMYFUNCTION("""COMPUTED_VALUE"""),"Itacaruaré") -> Itacaruaré | G32: =IFERROR(__xludf.DUMMYFUNCTION("""COMPUTED_VALUE"""),"Primero") -> Primero
A33: =IFERROR(__xludf.DUMMYFUNCTION("""COMPUTED_VALUE"""),45947.740095810186) -> 45947.74 | B33: =IFERROR(__xludf.DUMMYFUNCTION("""COMPUTED_VALUE"""),"Medina Luisana Ailend") -> Medina Luisana Ailend | C33: =IFERROR(__xludf.DUMMYFUNCTION("""COMPUTED_VALUE"""),"52739062") -> 52739062 | D33: =IFERROR(__xludf.DUMMYFUNCTION("""COMPUTED_VALUE"""),12.0) -> 12 | E33: =IFERROR(__xludf.DUMMYFUNCTION("""COMPUTED_VALUE"""),"Itacaruaré") -> Itacaruaré | G33: =IFERROR(__xludf.DUMMYFUNCTION("""COMPUTED_VALUE"""),"Primero") -> Primero
A34: =IFERROR(__xludf.DUMMYFUNCTION("""COMPUTED_VALUE"""),45944.36437326389) -> 45944.364 | B34: =IFERROR(__xludf.DUMMYFUNCTION("""COMPUTED_VALUE"""),"Renata Valentina Llamosas ") -> Renata Valentina Llamosas | C34: =IFERROR(__xludf.DUMMYFUNCTION("""COMPUTED_VALUE"""),"52309302") -> 52309302 | D34: =IFERROR(__xludf.DUMMYFUNCTION("""COMPUTED_VALUE"""),13.0) -> 13 | E34: =IFERROR(__xludf.DUMMYFUNCTION("""COMPUTED_VALUE"""),"Itacaruaré") -> Itacaruaré | G34: =IFERROR(__xludf.DUMMYFUNCTION("""COMPUTED_VALUE"""),"Primero") -> Primero
A35: =IFERROR(__xludf.DUMMYFUNCTION("""COMPUTED_VALUE"""),45947.716001458335) -> 45947.716 | B35: =IFERROR(__xludf.DUMMYFUNCTION("""COMPUTED_VALUE"""),"Rizzello Valentina Aylen") -> Rizzello Valentina Aylen | C35: =IFERROR(__xludf.DUMMYFUNCTION("""COMPUTED_VALUE"""),"55343203") -> 55343203 | D35: =IFERROR(__xludf.DUMMYFUNCTION("""COMPUTED_VALUE"""),9.0) -> 9 | E35: =IFERROR(__xludf.DUMMYFUNCTION("""COMPUTED_VALUE"""),"Itacaruaré") -> Itacaruaré | G35: =IFERROR(__xludf.DUMMYFUNCTION("""COMPUTED_VALUE"""),"Primero") -> Primero
A36: =IFERROR(__xludf.DUMMYFUNCTION("""COMPUTED_VALUE"""),45947.93515608796) -> 45947.935 | B36: =IFERROR(__xludf.DUMMYFUNCTION("""COMPUTED_VALUE"""),"Rodríguez de Oliveira Solange María ") -> Rodríguez de Oliveira Solange María | C36: =IFERROR(__xludf.DUMMYFUNCTION("""COMPUTED_VALUE"""),"34802897") -> 34802897 | D36: =IFERROR(__xludf.DUMMYFUNCTION("""COMPUTED_VALUE"""),34.0) -> 34 | E36: =IFERROR(__xludf.DUMMYFUNCTION("""COMPUTED_VALUE"""),"Itacaruaré") -> Itacaruaré | H36: =IFERROR(__xludf.DUMMYFUNCTION("""COMPUTED_VALUE"""),"Diploma") -> Diploma
A37: =IFERROR(__xludf.DUMMYFUNCTION("""COMPUTED_VALUE"""),45944.45419179398) -> 45944.454 | B37: =IFERROR(__xludf.DUMMYFUNCTION("""COMPUTED_VALUE"""),"Rodríguez Do Santos Milagros Ludmila") -> Rodríguez Do Santos Milagros Ludmila | C37: =IFERROR(__xludf.DUMMYFUNCTION("""COMPUTED_VALUE"""),"53963725") -> 53963725 | D37: =IFERROR(__xludf.DUMMYFUNCTION("""COMPUTED_VALUE"""),10.0) -> 10 | E37: =IFERROR(__xludf.DUMMYFUNCTION("""COMPUTED_VALUE"""),"Itacaruaré") -> Itacaruaré | G37: =IFERROR(__xludf.DUMMYFUNCTION("""COMPUTED_VALUE"""),"Primero") -> Primero
A38: =IFERROR(__xludf.DUMMYFUNCTION("""COMPUTED_VALUE"""),45944.45523850694) -> 45944.455 | B38: =IFERROR(__xludf.DUMMYFUNCTION("""COMPUTED_VALUE"""),"Scromeda Do Santos Abigail Ariadna") -> Scromeda Do Santos Abigail Ariadna | C38: =IFERROR(__xludf.DUMMYFUNCTION("""COMPUTED_VALUE"""),"52303419") -> 52303419 | D38: =IFERROR(__xludf.DUMMYFUNCTION("""COMPUTED_VALUE"""),13.0) -> 13 | E38: =IFERROR(__xludf.DUMMYFUNCTION("""COMPUTED_VALUE"""),"Itacaruaré") -> Itacaruaré | G38: =IFERROR(__xludf.DUMMYFUNCTION("""COMPUTED_VALUE"""),"Primero") -> Primero
A39: =IFERROR(__xludf.DUMMYFUNCTION("""COMPUTED_VALUE"""),45947.71234034722) -> 45947.712 | B39: =IFERROR(__xludf.DUMMYFUNCTION("""COMPUTED_VALUE"""),"Sosa Aylen Elizabeth") -> Sosa Aylen Elizabeth | C39: =IFERROR(__xludf.DUMMYFUNCTION("""COMPUTED_VALUE"""),"52309305") -> 52309305 | D39: =IFERROR(__xludf.DUMMYFUNCTION("""COMPUTED_VALUE"""),13.0) -> 13 | E39: =IFERROR(__xludf.DUMMYFUNCTION("""COMPUTED_VALUE"""),"Itacaruaré") -> Itacaruaré | G39: =IFERROR(__xludf.DUMMYFUNCTION("""COMPUTED_VALUE"""),"Primero") -> Primero
A40: =IFERROR(__xludf.DUMMYFUNCTION("""COMPUTED_VALUE"""),45978.733970960646) -> 45978.734 | B40: =IFERROR(__xludf.DUMMYFUNCTION("""COMPUTED_VALUE"""),"Brenda Nacimento ") -> Brenda Nacimento | C40: =IFERROR(__xludf.DUMMYFUNCTION("""COMPUTED_VALUE"""),"53536509") -> 53536509 | D40: =IFERROR(__xludf.DUMMYFUNCTION("""COMPUTED_VALUE"""),12.0) -> 12 | E40: =IFERROR(__xludf.DUMMYFUNCTION("""COMPUTED_VALUE"""),"Itacaruaré") -> Itacaruaré | G40: =IFERROR(__xludf.DUMMYFUNCTION("""COMPUTED_VALUE"""),"Primero") -> Primero
A41: =IFERROR(__xludf.DUMMYFUNCTION("""COMPUTED_VALUE"""),45944.555189907405) -> 45944.555 | B41: =IFERROR(__xludf.DUMMYFUNCTION("""COMPUTED_VALUE"""),"De Morais Keila Ayelen") -> De Morais Keila Ayelen | C41: =IFERROR(__xludf.DUMMYFUNCTION("""COMPUTED_VALUE"""),"54536877") -> 54536877 | D41: =IFERROR(__xludf.DUMMYFUNCTION("""COMPUTED_VALUE"""),10.0) -> 10 | E41: =IFERROR(__xludf.DUMMYFUNCTION("""COMPUTED_VALUE"""),"San Javier") -> San Javier | F41: =IFERROR(__xludf.DUMMYFUNCTION("""COMPUTED_VALUE"""),"Primero") -> Primero
A42: =IFERROR(__xludf.DUMMYFUNCTION("""COMPUTED_VALUE"""),45944.553714560185) -> 45944.554 | B42: =IFERROR(__xludf.DUMMYFUNCTION("""COMPUTED_VALUE"""),"De Morais Ornela ") -> De Morais Ornela | C42: =IFERROR(__xludf.DUMMYFUNCTION("""COMPUTED_VALUE"""),"50569580") -> 50569580 | D42: =IFERROR(__xludf.DUMMYFUNCTION("""COMPUTED_VALUE"""),14.0) -> 14 | E42: =IFERROR(__xludf.DUMMYFUNCTION("""COMPUTED_VALUE"""),"San Javier") -> San Javier | F42: =IFERROR(__xludf.DUMMYFUNCTION("""COMPUTED_VALUE"""),"Primero") -> Primero
A43: =IFERROR(__xludf.DUMMYFUNCTION("""COMPUTED_VALUE"""),45945.46596512731) -> 45945.466 | B43: =IFERROR(__xludf.DUMMYFUNCTION("""COMPUTED_VALUE"""),"Rodríguez Héctor Leandro ") -> Rodríguez Héctor Leandro | C43: =IFERROR(__xludf.DUMMYFUNCTION("""COMPUTED_VALUE"""),"54035639") -> 54035639 | D43: =IFERROR(__xludf.DUMMYFUNCTION("""COMPUTED_VALUE"""),11.0) -> 11 | E43: =IFERROR(__xludf.DUMMYFUNCTION("""COMPUTED_VALUE"""),"San Javier") -> San Javier | F43: =IFERROR(__xludf.DUMMYFUNCTION("""COMPUTED_VALUE"""),"Primero") -> Primero
A44: =IFERROR(__xludf.DUMMYFUNCTION("""COMPUTED_VALUE"""),45944.417542951385) -> 45944.418 | B44: =IFERROR(__xludf.DUMMYFUNCTION("""COMPUTED_VALUE"""),"Vasquez Alba Elena") -> Vasquez Alba Elena | C44: =IFERROR(__xludf.DUMMYFUNCTION("""COMPUTED_VALUE"""),"53795666") -> 53795666 | D44: =IFERROR(__xludf.DUMMYFUNCTION("""COMPUTED_VALUE"""),11.0) -> 11 | E44: =IFERROR(__xludf.DUMMYFUNCTION("""COMPUTED_VALUE"""),"San Javier") -> San Javier | F44: =IFERROR(__xludf.DUMMYFUNCTION("""COMPUTED_VALUE"""),"Primero") -> Primero
A45: =IFERROR(__xludf.DUMMYFUNCTION("""COMPUTED_VALUE"""),45944.46031371527) -> 45944.46 | B45: =IFERROR(__xludf.DUMMYFUNCTION("""COMPUTED_VALUE"""),"Ariana Aylin Galvan") -> Ariana Aylin Galvan | C45: =IFERROR(__xludf.DUMMYFUNCTION("""COMPUTED_VALUE"""),"54484198") -> 54484198 | D45: =IFERROR(__xludf.DUMMYFUNCTION("""COMPUTED_VALUE"""),10.0) -> 10 | E45: =IFERROR(__xludf.DUMMYFUNCTION("""COMPUTED_VALUE"""),"San Javier") -> San Javier | F45: =IFERROR(__xludf.DUMMYFUNCTION("""COMPUTED_VALUE"""),"Segundo") -> Segundo
A46: =IFERROR(__xludf.DUMMYFUNCTION("""COMPUTED_VALUE"""),45957.39104803241) -> 45957.391 | B46: =IFERROR(__xludf.DUMMYFUNCTION("""COMPUTED_VALUE"""),"de la Cruz Fernando Gabriel") -> de la Cruz Fernando Gabriel | C46: =IFERROR(__xludf.DUMMYFUNCTION("""COMPUTED_VALUE"""),"52808423") -> 52808423 | D46: =IFERROR(__xludf.DUMMYFUNCTION("""COMPUTED_VALUE"""),12.0) -> 12 | E46: =IFERROR(__xludf.DUMMYFUNCTION("""COMPUTED_VALUE"""),"San Javier") -> San Javier | F46: =IFERROR(__xludf.DUMMYFUNCTION("""COMPUTED_VALUE"""),"Segundo") -> Segundo
A47: =IFERROR(__xludf.DUMMYFUNCTION("""COMPUTED_VALUE"""),45944.67875510416) -> 45944.679 | B47: =IFERROR(__xludf.DUMMYFUNCTION("""COMPUTED_VALUE"""),"De Mattos Renzo Nahuel") -> De Mattos Renzo Nahuel | C47: =IFERROR(__xludf.DUMMYFUNCTION("""COMPUTED_VALUE"""),"53540265") -> 53540265 | D47: =IFERROR(__xludf.DUMMYFUNCTION("""COMPUTED_VALUE"""),11.0) -> 11 | E47: =IFERROR(__xludf.DUMMYFUNCTION("""COMPUTED_VALUE"""),"San Javier") -> San Javier | F47: =IFERROR(__xludf.DUMMYFUNCTION("""COMPUTED_VALUE"""),"Segundo") -> Segundo
A48: =IFERROR(__xludf.DUMMYFUNCTION("""COMPUTED_VALUE"""),45944.922296226854) -> 45944.922 | B48: =IFERROR(__xludf.DUMMYFUNCTION("""COMPUTED_VALUE"""),"Diana Aylen Márquez ") -> Diana Aylen Márquez | C48: =IFERROR(__xludf.DUMMYFUNCTION("""COMPUTED_VALUE"""),"53536588") -> 53536588 | D48: =IFERROR(__xludf.DUMMYFUNCTION("""COMPUTED_VALUE"""),11.0) -> 11 | E48: =IFERROR(__xludf.DUMMYFUNCTION("""COMPUTED_VALUE"""),"San Javier") -> San Javier | F48: =IFERROR(__xludf.DUMMYFUNCTION("""COMPUTED_VALUE"""),"Segundo") -> Segundo
A49: =IFERROR(__xludf.DUMMYFUNCTION("""COMPUTED_VALUE"""),45944.37807142361) -> 45944.378 | B49: =IFERROR(__xludf.DUMMYFUNCTION("""COMPUTED_VALUE"""),"Indira Speyer") -> Indira Speyer | C49: =IFERROR(__xludf.DUMMYFUNCTION("""COMPUTED_VALUE"""),"53795137") -> 53795137 | D49: =IFERROR(__xludf.DUMMYFUNCTION("""COMPUTED_VALUE"""),11.0) -> 11 | E49: =IFERROR(__xludf.DUMMYFUNCTION("""COMPUTED_VALUE"""),"San Javier") -> San Javier | F49: =IFERROR(__xludf.DUMMYFUNCTION("""COMPUTED_VALUE"""),"Segundo") -> Segundo
A50: =IFERROR(__xludf.DUMMYFUNCTION("""COMPUTED_VALUE"""),45944.58724586805) -> 45944.587 | B50: =IFERROR(__xludf.DUMMYFUNCTION("""COMPUTED_VALUE"""),"Mezetti Naieli Sofia ") -> Mezetti Naieli Sofia | C50: =IFERROR(__xludf.DUMMYFUNCTION("""COMPUTED_VALUE"""),"55699017") -> 55699017 | D50: =IFERROR(__xludf.DUMMYFUNCTION("""COMPUTED_VALUE"""),9.0) -> 9 | E50: =IFERROR(__xludf.DUMMYFUNCTION("""COMPUTED_VALUE"""),"San Javier") -> San Javier | F50: =IFERROR(__xludf.DUMMYFUNCTION("""COMPUTED_VALUE"""),"Segundo") -> Segundo
A51: =IFERROR(__xludf.DUMMYFUNCTION("""COMPUTED_VALUE"""),45944.347719537036) -> 45944.348 | B51: =IFERROR(__xludf.DUMMYFUNCTION("""COMPUTED_VALUE"""),"Segovia,Victoria Ayelen") -> Segovia,Victoria Ayelen | C51: =IFERROR(__xludf.DUMMYFUNCTION("""COMPUTED_VALUE"""),"55400685") -> 55400685 | D51: =IFERROR(__xludf.DUMMYFUNCTION("""COMPUTED_VALUE"""),9.0) -> 9 | E51: =IFERROR(__xludf.DUMMYFUNCTION("""COMPUTED_VALUE"""),"San Javier") -> San Javier | F51: =IFERROR(__xludf.DUMMYFUNCTION("""COMPUTED_VALUE"""),"Segundo") -> Segundo
A52: =IFERROR(__xludf.DUMMYFUNCTION("""COMPUTED_VALUE"""),46192.81131256944) -> 46192.811 | B52: =IFERROR(__xludf.DUMMYFUNCTION("""COMPUTED_VALUE"""),"Aguirre Guadalupe Xiomara") -> Aguirre Guadalupe Xiomara | C52: =IFERROR(__xludf.DUMMYFUNCTION("""COMPUTED_VALUE"""),"55617160") -> 55617160 | D52: =IFERROR(__xludf.DUMMYFUNCTION("""COMPUTED_VALUE"""),9.0) -> 9 | E52: =IFERROR(__xludf.DUMMYFUNCTION("""COMPUTED_VALUE"""),"Arroyo del Medio") -> Arroyo del Medio | F52: =IFERROR(__xludf.DUMMYFUNCTION("""COMPUTED_VALUE"""),"Segundo") -> Segundo
A53: =IFERROR(__xludf.DUMMYFUNCTION("""COMPUTED_VALUE"""),46192.82085270833) -> 46192.821 | B53: =IFERROR(__xludf.DUMMYFUNCTION("""COMPUTED_VALUE"""),"Leites Gimena Aylin ") -> Leites Gimena Aylin | C53: =IFERROR(__xludf.DUMMYFUNCTION("""COMPUTED_VALUE"""),"54232826") -> 54232826 | D53: =IFERROR(__xludf.DUMMYFUNCTION("""COMPUTED_VALUE"""),11.0) -> 11 | E53: =IFERROR(__xludf.DUMMYFUNCTION("""COMPUTED_VALUE"""),"Arroyo del Medio") -> Arroyo del Medio | F53: =IFERROR(__xludf.DUMMYFUNCTION("""COMPUTED_VALUE"""),"Segundo") -> Segundo
A54: =IFERROR(__xludf.DUMMYFUNCTION("""COMPUTED_VALUE"""),46193.8785687037) -> 46193.879 | B54: =IFERROR(__xludf.DUMMYFUNCTION("""COMPUTED_VALUE"""),"De Morais Ornela") -> De Morais Ornela | C54: =IFERROR(__xludf.DUMMYFUNCTION("""COMPUTED_VALUE"""),"50569580") -> 50569580 | D54: =IFERROR(__xludf.DUMMYFUNCTION("""COMPUTED_VALUE"""),15.0) -> 15 | E54: =IFERROR(__xludf.DUMMYFUNCTION("""COMPUTED_VALUE"""),"San Javier") -> San Javier | F54: =IFERROR(__xludf.DUMMYFUNCTION("""COMPUTED_VALUE"""),"Segundo") -> Segundo
A55: =IFERROR(__xludf.DUMMYFUNCTION("""COMPUTED_VALUE"""),46195.85097871527) -> 46195.851 | B55: =IFERROR(__xludf.DUMMYFUNCTION("""COMPUTED_VALUE"""),"Arndt") -> Arndt | C55: =IFERROR(__xludf.DUMMYFUNCTION("""COMPUTED_VALUE"""),"56785780") -> 56785780 | D55: =IFERROR(__xludf.DUMMYFUNCTION("""COMPUTED_VALUE"""),11.0) -> 11 | E55: =IFERROR(__xludf.DUMMYFUNCTION("""COMPUTED_VALUE"""),"Alem") -> Alem | F55: =IFERROR(__xludf.DUMMYFUNCTION("""COMPUTED_VALUE"""),"Tercero") -> Tercero

Sheet formulario
A1: Marca temporal | B1: DNI | C1: Nombres y Apellido del Alumno | D1: Dirección de correo electrónico | E1: Edad | F1: Domicilio | G1: Teléfono de contacto | H1: Fecha de nacimiento | I1: Sede | J1: Talleres/Ballet | K1: Nivel | L1: NRO DE CUIT o DNI del Responsable (Padre, Madre o Tutor) | M1: Apellido y Nombre Responsable | N1: Curso / Nivel | O1: {=D:D} -> Dirección de correo electrónico | P1: {=B:B} -> DNI | Q1: Cuota
A2: 46050.716 | B2: 46388761 | C2: Naomi Nahir Gazal | D2: naogazal10@gmail.com | E2: 20 | F2: Barrio cámpora Mz H casa 4 | G2: 3754522753 | H2: 38392 | I2: Leandro N. Alem | J2: Ballet Bailar y Vivir | L2: 27463887611 | M2: Gazal Naomi | O2: naogazal10@gmail.com | P2: 46388761
A3: 46050.719 | B3: 42715605 | C3: Piñeiro Martín Alejandro | D3: martinchook17@gmail.com | E3: 25 | F3: Barrio cámpora Mz H casa 4 | G3: 3754439412 | H3: 36663 | I3: Leandro N. Alem | J3: Ballet Bailar y Vivir | L3: 20426156053 | M3: Piñeiro Martín | O3: martinchook17@gmail.com | P3: 42715605
A4: 46052.643 | B4: 55048458 | C4: Keyla Franco | D4: marianafranco1221@gmail.com | E4: 11 | F4: Barrio alem 2 casa 22 | G4: 3754533498 | H4: 42310 | I4: Leandro N. Alem | J4: Profesorado Infantil ( Desde 7 años) | K4: 1er Año Preparatorio | L4: 27364707490 | M4: Franco Mariana | O4: marianafranco1221@gmail.com | P4: 55048458
A5: 46058.431 | B5: 43528949 | C5: Cintia soledad Burg | D5: burgcintia1@gmail.com | E5: 25 | F5: Bonpland 311 | G5: 3754504509 | H5: 36595 | I5: Leandro N. Alem | J5: Profesorado/Instructorado Adultos (Desde 15 años) | K5: 1er Año Preparatorio | L5: 27435289490 | M5: Burg Cintia soledad | O5: burgcintia1@gmail.com | P5: 43528949
A6: 46062.521 | B6: 56240798 | C6: Tiziano Lautaro brites | D6: mcaraben@gmail.com | E6: 7 | F6: Barrio primero de mayo | G6: 3764759756 | H6: 43175 | I6: Cerro Azul | J6: Profesorado Infantil ( Desde 7 años) | K6: 1er Año Preparatorio | L6: 27392225388 | M6: Mariana Isabel caraben | O6: mcaraben@gmail.com | P6: 56240798
A7: 46062.693 | B7: 53796732 | C7: Benjamín Maximiliano Losanto | D7: marcelalosanto025@gmail.com | E7: 11 | F7: Bonpland 115 | G7: 3754432414 | H7: 41729 | I7: Leandro N. Alem | J7: Profesorado Infantil ( Desde 7 años) | K7: 3er Año Elemental | L7: 27419951787 | M7: Marcela Losanto | O7: marcelalosanto025@gmail.com | P7: 53796732
A8: 46062.811 | B8: 53090248 | C8: Candela Jazmín Wach | D8: rosciszewski22yamila@gmail.com | E8: 12 | F8: San Cayetano 228 | G8: 3754402554 | H8: 41379 | I8: Leandro N. Alem | J8: Profesorado Infantil ( Desde 7 años) | K8: 3er Año Preparatorio | L8: 27368931387 | M8: Rosciszewski Yamila | O8: rosciszewski22yamila@gmail.com | P8: 53090248
A9: 46071.468 | B9: 55617160 | C9: Guadalupe Xiomara Aguirre | D9: lilianabarboza57@gmail.com | E9: 9 | F9: Arroyo del medio lote 3 mzE | G9: 03754402825 | H9: 42682 | I9: Arroyo del Medio | J9: Profesorado Infantil ( Desde 7 años) | K9: 2do Año Preparatorio | L9: 23330733004 | M9: Barboza Liliana Ines | O9: lilianabarboza57@gmail.com | P9: 55617160
A10: 46077.496 | B10: 57607912 | C10: VICTORIA MACIEL KREISCHER | D10: soniakreischer@yahoo.com.ar | E10: 7 | F10: BUENOS AIRES 233 | G10: 3754478360 | H10: 43580 | I10: Leandro N. Alem | J10: Paisanitos ( Hasta 7 años Mixto) | L10: 27269872964 | M10: KREISCHER SONIA | O10: soniakreischer@yahoo.com.ar | P10: 57607912
A11: 46077.572 | B11: 52302885 | C11: Leite Triana Elizabeth | D11: roselizabert@gmail.com | E11: 13 | F11: Loteo fao lote 3 Mz 13 | G11: 3754457934 | H11: 41197 | I11: Leandro N. Alem | J11: Folklore un Lenguaje Artístico (+12) | L11: 27347947763 | M11: Leite Rosana Elizabet | O11: roselizabert@gmail.com | P11: 52302885
A12: 46077.641 | B12: 53785766 | C12: Zoe Alexia Frenna | D12: npf_886@hotmail.com | E12: 11 | F12: Avenida Güemes 678 | G12: 3754498204 | H12: 41850 | I12: Leandro N. Alem | J12: Folklore Creativo (-12) | L12: 31789982 | M12: Frenna Nicolás Paolo | O12: npf_886@hotmail.com | P12: 53785766
A13: 46077.792 | B13: 53785780 | C13: Ona Guillermina Arndt | D13: eugemino14@gmail.com | E13: 11 | F13: Juan Jose Paso 665 | G13: 3754431943 | H13: 41872 | I13: Leandro N. Alem | J13: Profesorado Infantil ( Desde 7 años) | K13: 3er Año Preparatorio | L13: 30078018 | M13: Miño Eugenia Ivana | O13: eugemino14@gmail.com | P13: 53785780
A14: 46077.866 | B14: 53536539 | C14: Romero Pona Luz Milagros | D14: maesro22romero@gmail.com | E14: 12 | F14: Barrio illia casa 109 | G14: 15466849 | H14: 41600 | I14: Leandro N. Alem | J14: Profesorado Infantil ( Desde 7 años) | K14: 3er Año Elemental | L14: 32609218 | M14: Romero Ester Pona Daniel | O14: maesro22romero@gmail.com | P14: 53536539
A15: 46079.675 | B15: 53785766 | C15: Zoe Alexia Frenna | D15: npf_886@hotmail.com | E15: 11 | F15: Avenida Güemes 678 Leandro N. Alem Misiones | G15: 3754498204 | H15: 40754 | I15: Leandro N. Alem | J15: Profesorado Infantil ( Desde 7 años) | K15: 3er Año Preparatorio | L15: 31789982 | M15: Frenna Nicolás Paolo | O15: npf_886@hotmail.com | P15: 53785766
A16: 46081.437 | B16: 56369053 | C16: Gia Amelie | D16: eugemino14@gmail.com | E16: 8 | F16: Juan jose paso 665 | G16: 3754431943 | H16: 42895 | I16: Leandro N. Alem | J16: Folklore Creativo (-12) | L16: 30078018 | M16: Miño Eugenia Ivana | O16: eugemino14@gmail.com | P16: 56369053
A17: 46081.757 | B17: 53796732 | C17: Benjamín Maximiliano Losanto | D17: marcelalosanto025@gmail.com | E17: 11 | F17: Bonpland 115 | G17: 3754432414 | H17: 41729 | I17: Leandro N. Alem | J17: Profesorado Infantil ( Desde 7 años) | K17: 3er Año Elemental | L17: 27419951787 | M17: Marcela yaquelin Losanto | O17: marcelalosanto025@gmail.com | P17: 53796732
A18: 46083.493 | B18: 52739073 | C18: Brenda Anahi Back | D18: sandraisabeldasilva1@gmail.com | E18: 13 | F18: Loteo Fao Lote 9 Mz6 | G18: 3754529218 | H18: 41241 | I18: Leandro N. Alem | J18: Folklore un Lenguaje Artístico (+12) | L18: 27330735355 | M18: Da Silva Sandra Isabel | O18: sandraisabeldasilva1@gmail.com | P18: 52739073
A19: 46083.699 | B19: 58733735 | C19: Noa Samara Duran Quensell | D19: silviaa.quensell@gmail.com | E19: 4 | F19: Juan Pablo ll Mz 143 casa 11 | G19: 3754451548 | H19: 44327 | I19: Leandro N. Alem | J19: Paisanitos ( Hasta 7 años Mixto) | L19: 32609356 | M19: Quensell silvia | O19: silviaa.quensell@gmail.com | P19: 58733735
A20: 46083.928 | B20: 53537483 | C20: Sofía Itati Cardozo Gómez Fernandez | D20: carlagofernandez1612@gmail.com | E20: 12 | F20: Itacaruare | G20: 3754495317 | H20: 41624 | I20: Itacaruaré | J20: Profesorado Infantil ( Desde 7 años) | K20: 2do Año Elemental | L20: 27372237444 | M20: Carla Gómez Fernandez | O20: carlagofernandez1612@gmail.com | P20: 53537483
A21: 46084.74 | B21: 52309302 | C21: Llamosas Renata Valentina | D21: andreaferreiraa7@gmail.com | E21: 13 | F21: Itacuruaré | G21: 3754491063 | H21: 41158 | I21: Itacaruaré | J21: Profesorado Infantil ( Desde 7 años) | K21: 2do Año Elemental | L21: 35012496 | M21: Ferreira Andrea Maricel | O21: andreaferreiraa7@gmail.com | P21: 52309302
A22: 46085.72 | B22: 55697881 | C22: Gianna Josefina Alarcón francesconi | D22: yan-y010@hotmail.com | E22: 9 | F22: San Javier 71 | G22: 3754526025 | H22: 42774 | I22: Leandro N. Alem | J22: Folklore Creativo (-12) | L22: 27311108243 | M22: Yanina Mariel francesconi | O22: yan-y010@hotmail.com | P22: 55697881
A23: 46088.373 | B23: 52300816 | C23: Da Rosa Luz Morena | D23: Marianadsrosa@gmail.com | E23: 14 | F23: Barrio El Progreso | G23: 3754436677 | H23: 40970 | I23: Itacaruaré | J23: Folklore un Lenguaje Artístico (+12) | L23: 32303956 | M23: Da Rosa Mariana | O23: Marianadsrosa@gmail.com | P23: 52300816
A24: 46088.721 | B24: 48266790 | C24: MELINA AYLÉN FERREIRA | D24: yaamiiisuarezz@gmail.com | E24: 18 | F24: Barrio ILLIA casa 128 | G24: 3754473017 | H24: 39485 | I24: Leandro N. Alem | J24: Profesorado/Instructorado Adultos (Desde 15 años) | K24: 1er Año Superior | L24: 31792126 | M24: SUÁREZ YAMILA | O24: yaamiiisuarezz@gmail.com | P24: 48266790
A25: 46090.414 | B25: 48266790 | C25: ferreira melina | D25: nelinferreira54@gmail.com | E25: 18 | F25: barrio illia 128 | G25: 3754473017 | H25: 39486 | I25: Leandro N. Alem | J25: Profesorado/Instructorado Adultos (Desde 15 años) | K25: 3er Año Elemental | L25: 31792126 | M25: yamila suarez | O25: nelinferreira54@gmail.com | P25: 48266790
A26: 46090.475 | B26: 41851970 | C26: Carballo Leonardo Sebastian | D26: leonardosebastiancarballo@gmail.com | E26: 26 | F26: Mayordomo olivera 1196 | G26: 3754406409 | H26: 36256 | I26: Leandro N. Alem | J26: Profesorado/Instructorado Adultos (Desde 15 años) | K26: 1er Año Elemental | L26: 41851970 | M26: Carballo Leonardo Sebastian | O26: leonardosebastiancarballo@gmail.com | P26: 41851970
A27: 46091.466 | B27: 58420837 | C27: Alma Milenna Piñeiro | D27: gladyspineiro92@gmail.com | E27: 5 | F27: Barrio Virgen del Rosario C.19 Mza B. Las Rosas L.N. Alem | G27: 3754525967 | H27: 44137 | I27: Leandro N. Alem | J27: Paisanitos ( Hasta 7 años Mixto) | L27: 45789908 | M27: Piñeiro Abril Soledad | O27: gladyspineiro92@gmail.com | P27: 58420837
A28: 46091.62 | B28: 55488299 | C28: Ghisleyne Mariel Pawluk | D28: carmenpolopawluk@gmail.com | E28: 9 | F28: Lote 632 (Itacaruare) | G28: 3754533553 | H28: 42583 | I28: Itacaruaré | J28: Profesorado Infantil ( Desde 7 años) | K28: 2do Año Preparatorio | L28: 27278880058 | M28: Polo, María del Carmen | O28: carmenpolopawluk@gmail.com | P28: 55488299
A29: 46091.874 | B29: 50662259 | C29: Piriz Horiana Nahiara | D29: horianapiriz@gmail.com | E29: 15 | F29: La corita | G29: 3758571983 | H29: 40553 | I29: La Corita | J29: Profesorado/Instructorado Adultos (Desde 15 años) | K29: 2do Año Preparatorio | L29: 31524709 | M29: Ferreira Andrea | O29: horianapiriz@gmail.com | P29: 50662259
A30: 46091.908 | B30: 55777006 | C30: Florencia Agustina Roballo | D30: fabiinesalvez@hotmail.com | E30: 9 | F30: Itacaruare Ruta Prov. N° 2 | G30: 3754402449 | H30: 42613 | I30: Itacaruaré | J30: Profesorado Infantil ( Desde 7 años) | K30: 2do Año Preparatorio | L30: 27326094612 | M30: Alvez Fabiana Ines | O30: fabiinesalvez@hotmail.com | P30: 55777006
A31: 46097.756 | B31: 58604845 | C31: Raffael Austyn Escalante | D31: rocio_noe25@outlook.com | E31: 5 | F31: Loteo Graf Lote U N°1 L.N.Alem | G31: 3764717379 | H31: 44251 | I31: Leandro N. Alem | J31: Paisanitos ( Hasta 7 años Mixto) | L31: 33926008 | M31: Márquez Rocío Noelia | O31: rocio_noe25@outlook.com | P31: 58604845
A32: 46098.836 | B32: 53796813 | C32: Thiago Francisco Ramos de matos | D32: roxanademattos@gmail.com | E32: 11 | F32: Itacaruare | G32: 3754527738 | H32: 41718 | I32: Itacaruaré | J32: Profesorado Infantil ( Desde 7 años) | K32: 1er Año Preparatorio | L32: 39225800 | M32: Roxana andrea ramos de matto | O32: roxanademattos@gmail.com | P32: 53796813
A33: 46100.542 | B33: 52301700 | C33: Xiomara Belen Aguilera | D33: britezmarina966@gmail.com | E33: 13 | F33: Mateo estacala RN°2 | G33: 3754478246 | H33: 41358 | I33: Itacaruaré | J33: Profesorado Infantil ( Desde 7 años) | K33: 1er Año Preparatorio | L33: 37325768 | M33: Britez marina mablel | O33: britezmarina966@gmail.com | P33: 52301700
A34: 46112.307 | B34: 34896657 | C34: Sanabria Benjamín Fernando | D34: fernalop90@gmail.com | E34: 10 | F34: Juana konopka y Unión nacional 1506 | G34: 3754434865 | H34: 42328 | I34: Leandro N. Alem | J34: Folklore un Lenguaje Artístico (+12) | L34: 27348966575 | M34: Piñeiro Fernanda Lorey | O34: fernalop90@gmail.com | P34: 34896657
A35: 46112.358 | B35: 53963778 | C35: Rodríguez Sofía Itati | D35: yaninaalmeida535@gmail.com | E35: 9 | F35: Manuel Alvares y Sarmiento | G35: 3754476413 | H35: 42514 | I35: Itacaruaré | J35: Profesorado Infantil ( Desde 7 años) | K35: 2do Año Preparatorio | L35: 27348968624 | M35: Almeida Yanina | O35: yaninaalmeida535@gmail.com | P35: 53963778
A36: 46113.897 | B36: 55777087 | C36: Ayala Erik Benjamin | D36: scromedavanessa@gmail.com | E36: 8 | F36: Calle San Lorenzo Itacaruaré | G36: 3754533742 | H36: 42858 | I36: Itacaruaré | J36: Folklore Creativo (-12) | L36: 37223782 | M36: Scromeda Vanesa/Ayala Jose Luis | O36: scromedavanessa@gmail.com | P36: 55777087
A37: 46114.549 | B37: 43331812 | C37: Natali Yaquelin Baez | D37: yaquelinbaez845@gmail.com | E37: 24 | F37: L.CROCCE S/N L-11 | G37: 3765075392 | H37: 46118 | I37: Cerro Azul | J37: Profesorado/Instructorado Adultos (Desde 15 años) | K37: 2do Año Preparatorio | L37: 28552258 | M37: Rosa Graciela Ramos | O37: yaquelinbaez845@gmail.com | P37: 43331812
A38: 46118.587 | B38: 37473721 | C38: Evelin Itatí Suarez | D38: eveliinszz@gmail.com | E38: 32 | F38: Sargento Cabral y Sarasola | G38: 3764728829 | H38: 34421 | I38: Cerro Azul | J38: Profesorado/Instructorado Adultos (Desde 15 años) | K38: 1er Año Preparatorio | L38: 37473721 | M38: Suarez Evelin Itatí | O38: eveliinszz@gmail.com | P38: 37473721
A39: 46118.597 | B39: 36456601 | C39: Yesica belen ferreyra | D39: yesicabelenferreyra5@gmail.com | E39: 32 | F39: Barrio sauer | G39: 3764672625 | H39: 38075 | I39: Cerro Azul | J39: Profesorado/Instructorado Adultos (Desde 15 años) | K39: 2do Año Preparatorio | L39: 27364566013 | M39: Ferreyra yesica belén | O39: yesicabelenferreyra5@gmail.com | P39: 36456601
A40: 46118.622 | B40: 36456529 | C40: Araujo Mariza Itatí | D40: marizaitatiaraujo@gmail.com | E40: 33 | F40: Cerro azul | G40: 3754527092 | H40: 34052 | I40: Cerro Azul | J40: Profesorado/Instructorado Adultos (Desde 15 años) | K40: 2do Año Preparatorio | L40: 27364565297 | M40: Araujo Mariza Itatí | O40: marizaitatiaraujo@gmail.com | P40: 36456529
A41: 46128.753 | B41: 58733745 | C41: Clohe Liz Kubiszen | D41: lizmalvaamaro@icloud.com | E41: 4 | F41: Ambay 136 | G41: 3754414522 | H41: 44355 | I41: Leandro N. Alem | J41: Paisanitos ( Hasta 7 años Mixto) | L41: 30752609 | M41: Amaro Liz malva | O41: lizmalvaamaro@icloud.com | P41: 58733745
A42: 46129.466 | B42: 42515010 | C42: Francesconi Agustina Nazarena | D42: agustinafrancesconi70@gmail.com | E42: 26 | F42: Cerro Azul | G42: 3764713429 | H42: 4/14/0000 | I42: Cerro Azul | J42: Profesorado/Instructorado Adultos (Desde 15 años) | K42: 2do Año Preparatorio | L42: 2742515010 | M42: Francesconi Agustina Nazarena | O42: agustinafrancesconi70@gmail.com | P42: 42515010
A43: 46129.548 | B43: 54867338 | C43: Victoria Yazmin Engers | D43: rojasclaraines123@gmail.com | E43: 10 | F43: Avenida San Martin | G43: 3754439836 | H43: 42254 | I43: Itacaruaré | J43: Profesorado Infantil ( Desde 7 años) | K43: 1er Año Preparatorio | L43: 28556510 | M43: Clara Ines Rojas | O43: rojasclaraines123@gmail.com | P43: 54867338
A44: 46130.464 | B44: 52300811 | C44: Engel malena belén | D44: martakunz59@gmail.com | E44: 14 | F44: 25 de mayo y san martin | G44: 3743498495 | H44: 40969 | I44: Leandro N. Alem | J44: Profesorado/Instructorado Adultos (Desde 15 años) | K44: 1er Año Preparatorio | L44: 26113130 | M44: Kunz marta francisca | O44: martakunz59@gmail.com | P44: 52300811
A45: 46135.532 | B45: 46390849 | C45: Ciro Benjamín Nolasco | D45: delimanoemi6@gmail.com | E45: 8 | F45: Barrio Campora mz G casa 10 | G45: 3754466398 | H45: 43195 | I45: Leandro N. Alem | J45: Paisanitos ( Hasta 7 años Mixto) | L45: 27285390341 | M45: De Lima Clara Noemi | O45: delimanoemi6@gmail.com | P45: 46390849
A46: 46149.544 | B46: 34234803 | C46: Leites Franco Emmanuel | D46: leitesfrancoemmanuel@gmail.com | E46: 32 | F46: Lote 197 Arroyo del Medio | G46: 3754465877 | H46: 34333 | I46: Leandro N. Alem | J46: Profesorado/Instructorado Adultos (Desde 15 años) | K46: 3er Año Elemental | L46: 34234803 | M46: Leites Franco | O46: leitesfrancoemmanuel@gmail.com | P46: 34234803
A47: 46163.879 | B47: 34422662 | C47: Sol Betiana Yagus | D47: giselaantonietaalvez2@gmail.com | E47: 11 | F47: Cataratas del Iguazú 780 | G47: 3754441392 | H47: 41838 | I47: Leandro N. Alem | J47: Folklore un Lenguaje Artístico (+12) | L47: 27344226223 | M47: Gisela Alvez | O47: giselaantonietaalvez2@gmail.com | P47: 34422662
A48: 46170.828 | B48: 56679080 | C48: Angelina Boronski Galarza | D48: andreaangelinagalarza7@gmail.com | E48: 8 | F48: Calle Haití | G48: 374437765 | H48: 43150 | I48: Leandro N. Alem | J48: Folklore Creativo (-12) | L48: 28539161 | M48: Galarza Andrea Angelina | O48: andreaangelinagalarza7@gmail.com | P48: 56679080
A49: 46176.359 | B49: 54716470 | C49: Melani Guadalupe Correa | D49: cabreramariaeugenia311@gmail.com | E49: 10 | F49: Barrio belgrano calle maestro amatta 77 | G49: 3764104866 | H49: 42273 | I49: Leandro N. Alem | J49: Folklore un Lenguaje Artístico (+12) | L49: 37159085 | M49: Arruda Maria Eugenia | O49: cabreramariaeugenia311@gmail.com | P49: 54716470
A50: 46182.57 | B50: 55617400 | C50: Francesca Aytana Sanabria | D50: alecorr28@gmail.com | E50: 10 | F50: Snarbach 134 | G50: 3754455583 | H50: 42518 | I50: Leandro N. Alem | J50: Profesorado Infantil ( Desde 7 años) | K50: 1er Año Preparatorio | L50: 36060802 | M50: Correa da Silva | O50: alecorr28@gmail.com | P50: 55617400
A51: 46191.802 | B51: 55046930 | C51: Francisco Nestor | D51: neguikpp@gmail.com | E51: 9 | F51: Mecking 256 | G51: 3754456868 | H51: 42821 | I51: Leandro N. Alem | J51: Folklore Creativo (-12) | L51: 34515584 | M51: Knipp Andrea Soledad | O51: neguikpp@gmail.com | P51: 55046930
A52: 46091.908 | B52: 56371122 | C52: Ana Paula Dallabrida | D52: soleocara28@gmail.com | E52: 8 | F52: Cristo Rey 608 | G52: 3764391815 | H52: 42954 | I52: Leandro N. Alem | J52: Folklore Creativo (-12) | L52: 27285926098 | M52: Ocampo Rafaela | N52: =J52&" "&K52 -> Folklore Creativo (-12) | O52: soleocara28@gmail.com | P52: 56371122
A53: 46118.597 | B53: 11111111 | C53: Amelia Fernanda Leal | D53: andersenrafaela@gmail.com | E53: 5 | F53: gobernadores 1575 | G53: 3754659925 | H53: 44256 | I53: Leandro N. Alem | J53: Paisanitos ( Hasta 7 años Mixto) | L53: 23317902514 | M53: Andersen Rafaela | N53: =J53&" "&K53 -> Paisanitos ( Hasta 7 años Mixto) | O53: andersenrafaela@gmail.com | P53: 11111111
A54: 46118.597 | B54: 22222222 | C54: Rocio Hupan | D54: mariayandreshupan@gmail.com | E54: 10 | F54: av. Belgrano 1033 | G54: 3754419221 | H54: 42326 | I54: Leandro N. Alem | J54: Folklore Creativo (-12) | M54: Noelia Hupan | N54: =J54&" "&K54 -> Folklore Creativo (-12) | O54: mariayandreshupan@gmail.com | P54: 22222222
A55: 46118.597 | B55: 33333333 | C55: Isabella Hupan | D55: mariayandreshupan@gmail.com | E55: 10 | F55: av. Belgrano 1033 | G55: 3754419221 | H55: 42326 | I55: Leandro N. Alem | J55: Folklore Creativo (-12) | M55: Noelia Hupan | N55: =J55&" "&K55 -> Folklore Creativo (-12) | O55: mariayandreshupan@gmail.com | P55: 33333333
N56: =J56&" "&K56
N57: =J57&" "&K57

Sheet Planilla San Javier
A1: Instituto Para el Desarrollo del Arte
A2: "Danzas Folkloricas Argentinas"
A3: PROFESORA: | B3: ANDREA ANDRIOLI
A4: Sede: | B4: SAN JAVIER
A5: Año: | B5: 2025
A8: Nivel | B8: Apellido y Nombre | C8: DNI | D8: Zapateo | E8: Zarandeo | F8: Teoría | G8: Posición | H8: Expresión | I8: Danza | J8: Prom/Final
A9: 1ro Preparatorio | B9: De Morais Keila Ayelen | C9: 54536877
A10: 1ro Preparatorio | B10: De Morais Ornela | C10: 50569580
A11: 1ro Preparatorio | B11: Rodríguez Héctor Leandro | C11: 54035639
A12: 1ro Preparatorio | B12: Vasquez Alba Elena | C12: 53795666
A13: 2do Preparatorio | B13: Ariana Aylin Galvan | C13: 54484198
A14: 2do Preparatorio | B14: de la Cruz Fernando Gabriel | C14: 52808423
A15: 2do Preparatorio | B15: De Mattos Renzo Nahuel | C15: 53540265
A16: 2do Preparatorio | B16: Diana Aylen Márquez | C16: 53536588
A17: 2do Preparatorio | B17: Indira Speyer | C17: 53795137
A18: 2do Preparatorio | B18: Mezetti Naieli Sofia | C18: 55699017
A19: 2do Preparatorio | B19: Segovia,Victoria Ayelen | C19: 55400685
A26: Observaciones
B30: =TODAY()+1 -> 46198
A37: ................................... | H37: ....................................

Sheet Planilla Itaca
A1: Instituto Para el Desarrollo del Arte
A2: "Danzas Folkloricas Argentinas"
A3: PROFESORA: | B3: SOLANGE RODRIGUEZ
A4: Sede: | B4: ITACARUARE
A5: Año: | B5: 2025
A8: Nivel | B8: Apellido y Nombre | C8: DNI | D8: Zapateo | E8: Zarandeo | F8: Teoría | G8: Posición | H8: Expresión | I8: Danza | J8: Prom/Final
A9: 1ro Preparatorio | B9: Cardozo Gómez Fernández Sofía itati | C9: 53537483
A10: 1ro Preparatorio | B10: Kohl de Oliveira William | C10: 53785767
A11: 1ro Preparatorio | B11: Medina Candela Lissel Oraide | C11: 55777016
A12: 1ro Preparatorio | B12: Pawluk Ghisleyne Mariel | C12: 55488299
A13: 1ro Preparatorio | B13: Roballo Florencia Agustina | C13: 55777006
A14: 1ro Preparatorio | B14: Rodríguez Sofia Itatí | C14: 53963778
A15: 2do Preparatorio | B15: Da Rosa Luz Morena | C15: 52300816
A16: 2do Preparatorio | B16: Rodriguez Ludmara Gisahi | C16: 51083733
A17: 1ro Elemental | B17: Candia Sabrina Yazmin | C17: 52173063
A18: 1ro Elemental | B18: Cavallo Ámbar Abril | C18: 52449851
A19: 1ro Elemental | B19: Medina Luisana Ailend | C19: 52739062
A20: 1ro Elemental | B20: Renata Valentina Llamosas | C20: 52309302
... A25: 1ro Elemental | B25: Brenda Nacimento | C25: 53536509
A27: Observaciones
B30: =TODAY()+1 -> 46198
A37: ................................... | H37: ....................................

Sheet Planilla Franco
A1: Instituto Para el Desarrollo del Arte
A2: "Danzas Folkloricas Argentinas"
A3: PROFESOR: | B3: FRANCO LEITES
A4: Sede: | B4: CERRO AZUL - ARROYO DEL MEDIO
A5: Año: | B5: 2025
A8: Nivel | B8: Apellido y Nombre | C8: DNI | D8: Zapateo | E8: Zarandeo | F8: Teoría | G8: Posición | H8: Expresión | I8: Danza | J8: Prom/Final
A9: 1ro Preparatorio | B9: Aguirre Guadalupe Xiomara | C9: 55617160
A10: 1ro Preparatorio | B10: Gimena Aylin Leites | C10: 54232826
A11: 1ro Preparatorio | B11: Araujo Mariza Itatí | C11: 36456529
A12: 1ro Preparatorio | B12: Báez Natali Yaquelin | C12: 43331812
A13: 1ro Preparatorio | B13: Ferreyra Yesica Belén | C13: 36456601
A14: 1ro Preparatorio | B14: Francesconi Agustina Nazarena | C14: 42515020
A27: Observaciones
B30: =TODAY()+1 -> 46198
A37: ................................... | H37: ....................................

Sheet Planilla Alem
A1: Instituto Para el Desarrollo del Arte
A2: "Danzas Folkloricas Argentinas"
A3: PROFESORAS: | B3: GRACIELA SILVA - MOIRA FRUTOS
A4: Sede: | B4: LEANDRO N. ALEM
A5: Año: | B5: 2025
A8: Nivel | B8: Apellido y Nombre | C8: DNI | D8: Zapateo | E8: Zarandeo | F8: Teoría | G8: Posición | H8: Expresión | I8: Danza | J8: Prom/Final
A9: 1ro Preparatorio | B9: Tereschuk Anibal Adrian | C9: 40197439
A10: 1ro Preparatorio | B10: Olexen Mariana Cinthia | C10: 42288209
A11: 2do Preparatorio | B11: Back Brenda Anahi | C11: 52739073
A12: 2do Preparatorio | B12: Carolina Belén Rominski | C12: 43831994
A13: 2do Preparatorio | B13: Hanna Denise Machado | C13: 52809887
A14: 2do Preparatorio | B14: Pufal Mariana Elizabeth | C14: 28539165
A15: 2do Preparatorio | B15: Wach Candela Jazmín | C15: 53090248
A16: 2do Preparatorio | B16: Arndt Ona Guillermina | C16: 53785780
A17: 2do Preparatorio | B17: Frenna Zoe Alexia | C17: 53785766
A18: 1ro Elemental | B18: Leites Franco Emmanuel | C18: 34234803
A19: 2do Elemental | B19: Leites Franco Emmanuel | C19: 34234803
A20: 2do Elemental | B20: Benjamin Maximiliano Losanto | C20: 53796732
A21: 2do Elemental | B21: Luz Milagros Pona Romero | C21: 53536539
A22: 2do Elemental | B22: Josías Pablo Turcheñuk | C22: 50939930
A23: 2do Elemental | B23: Helena Anastasia Turcheñuk | C23: 53092554
A24: 2do Elemental | B24: Yasmin Araceli Cerdan | C24: 53092552
A25: Diploma Superior | B25: Rodríguez de Oliveira Solange María | C25: 34802897
A26: Diploma Superior | B26: Roballo Antonela Itatí | C26: 41506733
A27: Observaciones
B30: =TODAY()+1 -> 46198
A37: ................................... | H37: ....................................

Sheet CUIT
A1: 45726 | B1: Factura C | C1: 0002-00000043 | D1: CUIT | E1: 27415067335 | F1: 75108341951082 | G1: 10000 | H1: ROBALLO ANTONELA ITATI
A2: 45727 | B2: Factura C | C2: 0002-00000044 | D2: CUIT | E2: 27269872964 | F2: 75108432394962 | G2: 10000 | H2: KREISCHER SONIA ELBA
A3: 45727 | B3: Factura C | C3: 0002-00000045 | D3: CUIT | E3: 27269872964 | F3: 75108432848403 | G3: 15000 | H3: KREISCHER SONIA ELBA
A4: 45727 | B4: Factura C | C4: 0002-00000046 | D4: CUIT | E4: 27368931387 | F4: 75108434009039 | G4: 28000 | H4: ROSCISZEWSKI YAMILA FABIANA
A5: 45727 | B5: Factura C | C5: 0002-00000047 | D5: CUIT | E5: 27387754984 | F5: 75108457592582 | G5: 10000 | H5: KONDRATZKY LUCIANA BELEN
A6: 45729 | B6: Factura C | C6: 0002-00000048 | D6: CUIT | E6: 27415067335 | F6: 75118684204851 | G6: 20000 | H6: ROBALLO ANTONELA ITATI
A7: 45741 | B7: Factura C | C7: 0002-00000054 | D7: CUIT | E7: 27372237444 | F7: 75128003367564 | G7: 28000 | H7: GOMEZ FERNANDEZ CARLA ITATI
A8: 45741 | B8: Factura C | C8: 0002-00000055 | D8: CUIT | E8: 20270760253 | F8: 75128006623729 | G8: 10000 | H8: TRINDADES ANGEL RAMON
A9: 45741 | B9: Factura C | C9: 0002-00000056 | D9: CUIT | E9: 27419951574 | F9: 75128006900501 | G9: 25000 | H9: MALISKO DAMARIS SOLEDAD
A10: 45741 | B10: Factura C | C10: 0002-00000057 | D10: CUIT | E10: 27438319943 | F10: 75128010057193 | G10: 30000 | H10: ROMINSKI CAROLINA BELEN
A11: 45741 | B11: Factura C | C11: 0002-00000058 | D11: CUIT | E11: 20323050520 | F11: 75128011857268 | G11: 40000 | H11: FERREIRA DA SILVA OSCAR ANIBAL
A12: 45741 | B12: Factura C | C12: 0002-00000059 | D12: CUIT | E12: 27326092180 | F12: 75128015336553 | G12: 28000 | H12: ROMERO MARIA ESTER
... A24: 45748 | B24: Factura C | C24: 0002-00000072 | D24: CUIT | E24: 27463887611 | F24: 75138022378007 | G24: 25000 | H24: GAZAL NAOMI NAHIR
A25: 45747 | B25: Factura C | C25: 0002-00000065 | D25: CUIT | E25: 30672380576 | F25: 75138829321711 | G25: 600000
A26: 45747 | B26: Nota de Crédito C | C26: 0002-00000002 | D26: CUIT | E26: 30672380576 | F26: 75138830196073 | G26: 600000
A27: 45747 | B27: Factura C | C27: 0002-00000066 | D27: CUIT | E27: 27285391658 | F27: 75138830244109 | G27: 20000 | H27: PUFAL MARIANA ELIZABETH
A28: 45747 | B28: Factura C | C28: 0002-00000067 | D28: CUIT | E28: 30672380576 | F28: 75138830347418 | G28: 600000
A29: 45748 | B29: Factura C | C29: 0002-00000068 | D29: CUIT | E29: 27372237444 | F29: 75138978054503 | G29: 18000 | H29: GOMEZ FERNANDEZ CARLA ITATI
A30: 45748 | B30: Factura C | C30: 0002-00000069 | D30: CUIT | E30: 27269872964 | F30: 75138979730419 | G30: 15000 | H30: KREISCHER SONIA ELBA
A31: 45748 | B31: Factura C | C31: 0002-00000070 | D31: CUIT | E31: 27285926098 | F31: 75138988479138 | G31: 25000 | H31: OCAMPO RAFAELA SOLEDAD
A32: 45754 | B32: Factura C | C32: 0002-00000073 | D32: CUIT | E32: 20342348034 | F32: 75148696870521 | G32: 30000 | H32: LEITES FRANCO EMMANUEL
A33: 45754 | B33: Factura C | C33: 0002-00000074 | D33: CUIT | E33: 27415067335 | F33: 75148697586486 | G33: 20000 | H33: ROBALLO ANTONELA ITATI
A34: 45754 | B34: Factura C | C34: 0002-00000075 | D34: CUIT | E34: 27348028974 | F34: 75148699050721 | G34: 30000 | H34: RODRIGUEZ DE OLIVERA SOLANGE MARIA
A35: 45757 | B35: Factura C | C35: 0002-00000077 | D35: CUIT | E35: 27295521592 | F35: 75158106306265 | G35: 18000 | H35: ALANIZ MARIANA HAYDEE
A36: 45757 | B36: Factura C | C36: 0002-00000078 | D36: CUIT | E36: 23307394774 | F36: 75158113569034 | G36: 25000 | H36: CANDIA DEIVIS MICHAEL
A37: 45757 | B37: Factura C | C37: 0002-00000079 | D37: CUIT | E37: 20323050520 | F37: 75158132235042 | G37: 40000 | H37: FERREIRA DA SILVA OSCAR ANIBAL
A38: 45757 | B38: Factura C | C38: 0002-00000080 | D38: CUIT | E38: 20342348034 | F38: 75158132847426 | G38: 20000 | H38: LEITES FRANCO EMMANUEL
A39: 45762 | B39: Factura C | C39: 0002-00000081 | D39: DNI | E39: 43831994 | F39: 75158595975652 | G39: 20000 | H39: ROMINSKI CAROLINA BELEN
A40: 45762 | B40: Factura C | C40: 0002-00000082 | D40: CUIT | E40: 27419951574 | F40: 75158623439554 | G40: 25000 | H40: MALISKO DAMARIS SOLEDAD
A41: 45762 | B41: Factura C | C41: 0002-00000083 | D41: CUIT | E41: 20430237714 | F41: 75158624014420 | G41: 25000 | H41: CANDIA DEIVIS MICHAEL
A42: 45762 | B42: Factura C | C42: 0002-00000084 | D42: Doc. (otro) | F42: 75158624594089 | G42: 15000
A43: 45762 | B43: Factura C | C43: 0002-00000085 | D43: CUIT | E43: 27463887611 | F43: 75158625182189 | G43: 25000 | H43: GAZAL NAOMI NAHIR
A44: 45762 | B44: Factura C | C44: 0002-00000086 | D44: CUIT | E44: 20430237714 | F44: 75158625629476 | G44: 25000 | H44: CANDIA DEIVIS MICHAEL
A45: 45762 | B45: Factura C | C45: 0002-00000087 | D45: CUIT | E45: 27357122401 | F45: 75158652414963 | G45: 15000 | H45: PIÑEIRO GLADYS ANDREA
A46: 45762 | B46: Nota de Crédito C | C46: 0002-00000003 | D46: CUIT | E46: 20430237714 | F46: 75158655792100 | G46: 25000 | H46: CANDIA DEIVIS MICHAEL
A47: 45756 | B47: Factura C | C47: 0002-00000076 | D47: CUIT | E47: 27330735355 | F47: 75158957980182 | G47: 18000 | H47: DA SILVA SANDRA ISABEL
A48: 45769 | B48: Factura C | C48: 0002-00000088 | D48: CUIT | E48: 27387753562 | F48: 75168344348543 | G48: 10000 | H48: LUIS DA SILVEYRA PAOLA
A49: 45778 | B49: Factura C | C49: 0002-00000089 | D49: CUIT | E49: 27269872964 | F49: 75188439480858 | G49: 15000 | H49: KREISCHER SONIA ELBA
A50: 45783 | B50: Factura C | C50: 0002-00000090 | D50: CUIT | E50: 30672380576 | F50: 75188950389885 | G50: 600000
A51: 45785 | B51: Factura C | C51: 0002-00000091 | D51: CUIT | E51: 33714503559 | F51: 75198306259478 | G51: 37500
A52: 45787 | B52: Factura C | C52: 0002-00000092 | D52: CUIT | E52: 27368931387 | F52: 75198547127466 | G52: 18000 | H52: ROSCISZEWSKI YAMILA FABIANA
A53: 45789 | B53: Factura C | C53: 0002-00000093 | D53: CUIT | E53: 27357122401 | F53: 75198801587455 | G53: 25000 | H53: PIÑEIRO GLADYS ANDREA
A54: 45789 | B54: Factura C | C54: 0002-00000094 | D54: DNI | E54: 43831994 | F54: 75198806629367 | G54: 20000 | H54: ROMINSKI CAROLINA BELEN
A55: 45791 | B55: Factura C | C55: 0002-00000095 | D55: CUIT | E55: 30707837752 | F55: 75208977346929 | G55: 9000
A56: 45798 | B56: Factura C | C56: 0002-00000096 | D56: CUIT | E56: 30503505998 | F56: 75218867676596 | G56: 20000
A57: 45798 | B57: Factura C | C57: 0002-00000097 | D57: CUIT | E57: 30546679183 | F57: 75218874375151 | G57: 26000
A58: 45810 | B58: Factura C | C58: 0002-00000098 | D58: CUIT | E58: 27463887611 | F58: 75228236436328 | G58: 15000 | H58: GAZAL NAOMI NAHIR
A59: 45811 | B59: Factura C | C59: 0002-00000099 | D59: CUIT | E59: 27269872964 | F59: 75228359967668 | G59: 18000 | H59: KREISCHER SONIA ELBA
A60: 45818 | B60: Factura C | C60: 0002-00000103 | D60: CUIT | E60: 27330735355 | F60: 75238337658860 | G60: 38000 | H60: DA SILVA SANDRA ISABEL
A61: 45818 | B61: Factura C | C61: 0002-00000104 | D61: CUIT | E61: 27330735355 | F61: 75238338242097 | G61: 18000 | H61: DA SILVA SANDRA ISABEL
A62: 45818 | B62: Factura C | C62: 0002-00000105 | D62: CUIT | E62: 27330735355 | F62: 75238341573114 | G62: 7000 | H62: DA SILVA SANDRA ISABEL
A63: 45818 | B63: Factura C | C63: 0002-00000106 | D63: CUIT | E63: 27368931387 | F63: 75238342074454 | G63: 23000 | H63: ROSCISZEWSKI YAMILA FABIANA
A64: 45818 | B64: Factura C | C64: 0002-00000107 | D64: CUIT | E64: 27295521592 | F64: 75238345945169 | G64: 38000 | H64: ALANIZ MARIANA HAYDEE
A65: 45818 | B65: Factura C | C65: 0002-00000108 | D65: CUIT | E65: 27300780186 | F65: 75238348598544 | G65: 56000 | H65: MIÑO EUGENIA IVANA
A66: 45818 | B66: Factura C | C66: 0002-00000109 | D66: DNI | E66: 43831994 | F66: 75238349851233 | G66: 20000 | H66: ROMINSKI CAROLINA BELEN
A67: 45818 | B67: Factura C | C67: 0002-00000110 | D67: DNI | E67: 43831994 | F67: 75238355815367 | G67: 25000 | H67: ROMINSKI CAROLINA BELEN
A68: 45814 | B68: Factura C | C68: 0002-00000100 | D68: CUIT | E68: 30546679183 | F68: 75238769824314 | G68: 86000
A69: 45814 | B69: Factura C | C69: 0002-00000101 | D69: CUIT | E69: 27348028974 | F69: 75238772089610 | G69: 40000 | H69: RODRIGUEZ DE OLIVERA SOLANGE MARIA
A70: 45814 | B70: Factura C | C70: 0002-00000102 | D70: CUIT | E70: 27415067335 | F70: 75238797261327 | G70: 25000 | H70: ROBALLO ANTONELA ITATI
A71: 45829 | B71: Factura C | C71: 0002-00000111 | D71: CUIT | E71: 27416961048 | F71: 75258566483148 | G71: 40000 | H71: BESLIBJAC ROCIO ELIZABETH
A72: 45833 | B72: Factura C | C72: 0002-00000112 | D72: CUIT | E72: 30607572948 | F72: 75268027090398 | G72: 567000
A73: 45833 | B73: Nota de Crédito C | C73: 0002-00000004 | D73: CUIT | E73: 30607572948 | F73: 75268035702510 | G73: 567000
A74: 45833 | B74: Factura C | C74: 0002-00000113 | D74: CUIT | E74: 30607572948 | F74: 75268036441927 | G74: 495000
A75: 45833 | B75: Factura C | C75: 0002-00000114 | D75: CUIT | E75: 30607572948 | F75: 75268039502683 | G75: 90360
A76: 45833 | B76: Nota de Crédito C | C76: 0002-00000005 | D76: CUIT | E76: 30607572948 | F76: 75268178099805 | G76: 90360
A77: 45834 | B77: Factura C | C77: 0002-00000115 | D77: CUIT | E77: 30607572948 | F77: 75268178858984 | G77: 90360
A78: 45838 | B78: Factura C | C78: 0002-00000116 | D78: CUIT | E78: 27415067335 | F78: 75268623971281 | G78: 90000 | H78: ROBALLO ANTONELA ITATI
A79: 45839 | B79: Factura C | C79: 0002-00000117 | D79: CUIT | E79: 27269872964 | F79: 75268731227683 | G79: 18000 | H79: KREISCHER SONIA ELBA
A80: 45845 | B80: Factura C | C80: 0002-00000119 | D80: CUIT | E80: 27415067335 | F80: 75278556963020 | G80: 25000 | H80: ROBALLO ANTONELA ITATI
A81: 45840 | B81: Factura C | C81: 0002-00000118 | D81: CUIT | E81: 27295521592 | F81: 75278850048506 | G81: 23000 | H81: ALANIZ MARIANA HAYDEE
A82: 45852 | B82: Factura C | C82: 0002-00000120 | D82: CUIT | E82: 27419951574 | F82: 75288449948657 | G82: 30000 | H82: MALISKO DAMARIS SOLEDAD
A83: 45874 | B83: Factura C | C83: 0002-00000121 | D83: CUIT | E83: 33714503559 | F83: 75318133995767 | G83: 28500
A84: 45876 | B84: Factura C | C84: 0002-00000122 | D84: CUIT | E84: 27415067335 | F84: 75328394322373 | G84: 25000 | H84: ROBALLO ANTONELA ITATI
A85: 45876 | B85: Factura C | C85: 0002-00000123 | D85: CUIT | E85: 30607572948 | F85: 75328396117616 | G85: 126000
A86: 45876 | B86: Factura C | C86: 0002-00000124 | D86: CUIT | E86: 27372237827 | F86: 75328401008302 | G86: 10000 | H86: SCROMEDA MACARENA VANESA
A87: 45876 | B87: Factura C | C87: 0002-00000125 | D87: CUIT | E87: 30607572948 | F87: 75328403198670 | G87: 126000
A88: 45876 | B88: Nota de Crédito C | C88: 0002-00000006 | D88: CUIT | E88: 30607572948 | F88: 75328403545340 | G88: 126000

Sheet Matriculas2022
A1: Marca temporal | B1: Dirección de correo electrónico | C1: Apellido y Nombre | D1: EDAD | E1: DNI | F1: Fecha de Nacimiento | G1: Domicilio | H1: Localidad | I1: Escuela a la que asiste y grado o curso | J1: Nombre del Padre/Madre | K1: Teléfono de contacto | L1: Ocupación | M1: Curso que elige | N1: Niveles [Preparatorios] | O1: Niveles [Elementales] | P1: Niveles [Superiores] | R1: Email | S1: Provincia
A2: 44592.919 | B2: flaviabeatrizleguizamon@gmail.com | C2: Leguizamón Flavia Beatriz. | D2: 22 | E2: 41694880 | F2: 36250 | G2: Mz 8, lote 6. Barrio Loteo Fao. | H2: Leandro N. Alem. | I2: Instituto Superior de Formación Docente. (PEP) 4to año. | J2: Lovera Liliana Beatriz y José Antonio Leguizamón. | K2: 3754465397 | L2: Estudiante. | M2: Danzas Folklóricas Argentina modalidad Acelerada (Mayores de 18 años) | N2: Primero, Segundo | R2: =B2 -> flaviabeatrizleguizamon@gmail.com | S2: Misiones
A3: 44592.922 | B3: yamila_oronah@hotmail.com | C3: Oronah yamila Alejandra | D3: 41 | E3: 28728075 | F3: 29610 | G3: Meliquina 256 cab. 2 | H3: San Martín de los Andes | K3: 1159805728 | L3: Tallerista | M3: Danzas Folklóricas Argentina modalidad Acelerada (Mayores de 18 años) | N3: Segundo, Tercero | R3: =B3 -> yamila_oronah@hotmail.com | S3: Neuquén
A4: 44593.469 | B4: roballoantonela@gmail.com | C4: Roballo Antonela Itatí | D4: 23 | E4: 41506733 | F4: 36076 | G4: La Corita | H4: Santa María | J4: Juan José Roballo/ Marta Beatriz De Andrade | K4: 3754430914 | L4: Docente | M4: Danzas Folklóricas Argentina modalidad Acelerada (Mayores de 18 años) | O4: Primero, Segundo | R4: =B4 -> roballoantonela@gmail.com | S4: Misiones
A5: 44593.539 | B5: ualejandra074@gmail.com | C5: Ulloa María Alejandra | D5: 47 | E5: 23726370 | F5: 27308 | G5: Calle cerro los ángeles 121 ,, cordones del Chapelco | H5: San martín de los Andes | K5: 2944380035 | L5: Educadora en primera Infancia | M5: Danzas Folklóricas Argentina modalidad Acelerada (Mayores de 18 años) | N5: Segundo | R5: =B5 -> ualejandra074@gmail.com | S5: Neuquén
A6: 44593.721 | B6: flor85pintodasilva@gmail.com | C6: Pinto Da Silva Florencia Guadalupe | D6: 36 | E6: 31572466 | F6: 31356 | G6: San Martín y fleming | H6: San Javier | K6: 3754470782 | L6: Docente | M6: Danzas Folklóricas Argentina modalidad Acelerada (Mayores de 18 años) | O6: Primero | R6: =B6 -> flor85pintodasilva@gmail.com | S6: Misiones
A7: 44594.396 | B7: marianaalaniz82@gmail.com | C7: Moschen, Lucas Martín | D7: 8 | E7: 53235744 | F7: 41506 | G7: Otto Bar 62 | H7: Leandro N.Alem | I7: Escuela N°62. Tercer grado | J7: Mariana Alaniz | K7: 3755410502 | L7: Docente | M7: Danzas Folklóricas Argentina modalidad Común (Niños q ya asistieron al taller) | N7: Primero | R7: =B7 -> marianaalaniz82@gmail.com | S7: Misiones
A8: 44594.399 | B8: marianaalaniz82@gmail.com | C8: Moschen, Paula Antonella | D8: 5 | E8: 55488253 | F8: 42514 | G8: Otto Bar 62 | H8: Leandro N.Alem | I8: Escuela 62. Primer grado | J8: Mariana Alaniz | K8: 3755410502 | L8: Docente | M8: Danzas Folklóricas Argentina modalidad Común (Niños q ya asistieron al taller) | N8: Primero | R8: =B8 -> marianaalaniz82@gmail.com | S8: Misiones
A9: 44615.866 | B9: marialaura.alzugaray@gmail.com | C9: Alzugaray Maria Laura | D9: 28 | E9: 37581526 | F9: 34174 | G9: Barrio Illia casa 84 | H9: Leandro N. Alem | K9: 3754472507 | L9: Profesora | M9: Danzas Folklóricas Argentina modalidad Acelerada (Mayores de 18 años) | O9: Primero | R9: =B9 -> marialaura.alzugaray@gmail.com | S9: Misiones
A10: 44617.472 | B10: bogadonilse452@gmail.com | C10: Bogado Nilse Noemi | D10: 33 | E10: 33639858 | F10: 32318 | G10: Barrio belgrano.manz103 | H10: Candelaria | K10: 3765016121 | L10: Empleada publica. Bibliotecaria | M10: Danzas Folklóricas Argentina modalidad Acelerada (Mayores de 18 años) | N10: Primero, Segundo, Tercero | R10: =B10 -> bogadonilse452@gmail.com | S10: Misiones
A11: 44622.535 | B11: centroesteticoalmabella@gmail.com | C11: Paniagua Nadia Belén | D11: 31 | E11: 35006709 | F11: 33085 | G11: Saavedra 112 | H11: Leandro N. Alem | J11: Alicia | K11: 3754461035 | L11: Estetisista- Maestra de Nivel Inicia. | M11: Danzas Folklóricas Argentina modalidad Acelerada (Mayores de 18 años) | O11: Primero, Segundo | R11: =B11 -> centroesteticoalmabella@gmail.com | S11: Misiones
A12: 44627.384 | B12: fdaluz83@gmail.com | C12: Da Luz Facundo Manuel | D12: 38 | E12: 30430962 | F12: 30670 | G12: Félix Durán 449 | H12: Leandro N. Alem | K12: 3754475271 | L12: Comerciante | M12: Danzas Folklóricas Argentina modalidad Acelerada (Mayores de 18 años) | O12: Tercero | R12: =B12 -> fdaluz83@gmail.com | S12: Misiones
A13: 44627.556 | B13: mabel17892810@hotmail.com.ar | C13: Luz Milagros Pona Romero | D13: 8 | E13: 53536539 | F13: 41600 | G13: Barrios Illia casa 109 | H13: Leandro N. Alem | I13: Espíritu Santo 3grado turno mañana | J13: María Ester Romero/ Esteban Daniel Pona | K13: 15466849 | L13: Administrativa | M13: Danzas Folklóricas Argentina modalidad Común (Niños q ya asistieron al taller) | N13: Segundo | R13: =B13 -> mabel17892810@hotmail.com.ar | S13: Misiones
A14: 44630.472 | B14: andreapedroski63@gmail.com | C14: Pedroski Andrea Soledad | D14: 26 | E14: 36474811 | F14: 35089 | G14: Almafuerte mz12 | H14: Almafuerte | K14: 3754430036 | L14: Empleada | M14: Danzas Folklóricas Argentina modalidad Acelerada (Mayores de 18 años) | O14: Primero, Segundo | R14: =B14 -> andreapedroski63@gmail.com | S14: Misiones
A15: 44634.668 | B15: patriciazipan5@gmail.com | C15: Zipan Luzmila yohana | D15: 15 | E15: 46997614 | F15: 39120 | G15: Bonpland misiones | H15: Bonpland | I15: IEA N1 | J15: Viviana | K15: 3765121638 | L15: Ama de casa | M15: Danzas Folklóricas Argentina modalidad Acelerada (Mayores de 18 años) | O15: Tercero | R15: =B15 -> patriciazipan5@gmail.com | S15: Misiones
A16: 44636.987 | B16: kreuningludmila@gmail.com | C16: Kreuning Ludmila Aymara | D16: 20 | E16: 43619349 | F16: 37258 | G16: Km 14 ruta 4 San Javier Misiones | H16: San Javier | I16: Escuela de comercio N5 primera imprenta | J16: Dora Eliza Piñeiro | K16: 3754527998 | L16: Estudio | M16: Danzas Folklóricas Argentina modalidad Acelerada (Mayores de 18 años) | N16: Primero, Segundo, Tercero, Diploma | R16: =B16 -> kreuningludmila@gmail.com | S16: Misiones
A17: 44637.926 | B17: kreuningrenata@gmail.com | C17: Kreuning Renata | D17: 16 | E17: 46387989 | F17: 38474 | G17: Km14 ruta N 4 San Javier Misiones | H17: San Javier | I17: Escuela de comercio N5 primera imprenta | J17: Dora Eliza Piñeiro | K17: 3754472949 | L17: Estudio | M17: Danzas Folklóricas Argentina modalidad Acelerada (Mayores de 18 años) | N17: Primero, Segundo, Tercero, Diploma | R17: =B17 -> kreuningrenata@gmail.com | S17: Misiones
A18: 44656.775 | B18: yiselfriedruch27@gmail.com | C18: Guzman Friedrich Emma Marilyn | D18: 9 | E18: 52064407 | F18: 41032 | G18: Lote 98 | H18: Almafuerte | I18: Escula 95. Curso 5to | J18: Friedrich Yisel | K18: 3754417124 | L18: Empleada doméstica | M18: Danzas Folklóricas Argentina modalidad Común (Niños q ya asistieron al taller) | N18: Primero
A19: 44657.759 | B19: yaninasuares876@gmail.com | C19: Suares Naiara Ayelen | D19: 11 | E19: 50681649 | F19: 40451 | G19: SN | H19: Santa maria | I19: Escuela n° 30 (la corita) grado 6 | J19: Yanina daiana suares | K19: 3758560556 | L19: Empleada doméstica | M19: Danzas Folklóricas Argentina modalidad Común (Niños q ya asistieron al taller) | N19: Primero
A20: 44657.761 | B20: yaninasuares876@gmail.com | C20: Suares Zoe Daiana Salomé | D20: 9 | E20: 52946108 | F20: 41291 | G20: SN | H20: Santa maria | I20: Escuela n°30 (la corita) grado 4 | J20: Suares Yanina daiana | K20: 3758560556 | L20: Empleada doméstica | M20: Danzas Folklóricas Argentina modalidad Común (Niños q ya asistieron al taller) | N20: Primero
A21: 44658.512 | B21: fsilvialiliana697@gmail.com | C21: Franco silvia liliana | D21: 58 | E21: 17164781 | F21: 23737 | G21: Ushuaia 85 | H21: Leandro n alem | I21: IDEAR | J21: Jose maria franco y angela gomez | K21: 3754504521 | L21: Docente | M21: Danzas Folklóricas Argentina modalidad Acelerada (Mayores de 18 años) | N21: Tercero
A22: 44659.501 | B22: patriciasolmelo15@gmail.com | C22: Do Santos Melo Milagros Catrina | D22: 9 | E22: 52740497 | F22: 41242 | G22: Mz 30 solar b | H22: Bonpland | I22: Escula 13 madre de pueblos. 4° grado | J22: Do Santos Sergio Abel, Melo Patricia Soledad | K22: 3765083656 | L22: Ama de casa | M22: Taller de Iniciación a las Danzas Folklóricas Argentinas (Niños)
A23: 44659.644 | B23: ag0036035@gmail.com | C23: Morena Antonia Acosta | D23: 8 | E23: 53363925 | F23: 41494 | G23: Manz 125 Roque Sáenz Peña y Mariano Moreno | H23: Candelaria | I23: Santa Cecilia N°285 | J23: Alejandra González | K23: 3764532317 | L23: Ama de casa | M23: Taller de Iniciación a las Danzas Folklóricas Argentinas (Niños)
A24: 44663.345 | B24: flor85pintodasilva@gmail.com | C24: Pinto Da Silva Florencia Guadalupe | D24: 36 | E24: 31572466 | F24: 31356 | G24: San Martín y fleming s/n | H24: San Javier | K24: 3754470782 | L24: Docente | M24: Danzas Folklóricas Argentina modalidad Acelerada (Mayores de 18 años) | N24: Tercero | P24: Primero
A25: 44665.619 | B25: vivianaago1972@gmail.com | C25: González Silvia Viviana | D25: 49 | E25: 22520325 | F25: 44666 | G25: Barrio 20 viviendas casa 01 mzna355 | H25: San Javier | I25: 3año IDEAR | K25: 3754400096 | L25: Docente | M25: Danzas Folklóricas Argentina modalidad Acelerada (Mayores de 18 años) | N25: Tercero
A26: 44676.729 | B26: soniapedroski153@gmail.com | C26: Zaira Valentina De silveria | D26: 9 años | E26: 52524591 | F26: 41114 | G26: Garupa colectora ruta 12 | H26: Garupa misiones | I26: Esperanza de la patria garupa grado 5to A turno mañana | J26: Madre Sonia Graciela pedroski | K26: 3764636682 | L26: Ama de casa | M26: Taller de Iniciación a las Danzas Folklóricas Argentinas (Niños)
A27: 44702.451 | B27: dominguezsilvani@gmail.com | C27: Silvani noemi, Domínguez Pereira | D27: 31 | E27: 35008567 | F27: 33272 | G27: Barrio juan pablo II. casa 16 manzana 141 | H27: Leandro N Alem. | I27: Normal Superior N1. profesorado de educación primaria. 3 año | J27: Raúl e Isabel. | K27: 3754471291 | L27: Estudiante | M27: Danzas Folklóricas Argentina modalidad Acelerada (Mayores de 18 años)
A28: 45219.484 | B28: leitesfrancoemmanuel@gmail.com | C28: Leites Franco Emmanuel | D28: 29 | E28: 34234803 | F28: 34333 | G28: Lote N° 197 | H28: Arroyo del Medio | I28: Cep N° 29 | K28: 3765141507 | L28: Modisto | M28: Danzas Folklóricas Argentina modalidad Acelerada (Mayores de 18 años) | P28: Primero, Segundo, Tercero
A29: 45224.364 | B29: espindolasilvina11@gmail.com | C29: Espíndola Silvina Andrea | D29: 37 | E29: 31789911 | F29: 31547 | G29: Candelaria 973 | H29: Leandro N Alem | I29: Secundaria completa Esc Normal superior N1 | J29: De sosa Amalia | K29: 3754467341 | L29: Ama de casa | M29: Danzas Folklóricas Argentina modalidad Acelerada (Mayores de 18 años) | N29: Primero
A30: 45230.648 | B30: eva14@live.com.ar | C30: Daldovo Zuetta, Lucero Belén | D30: 9 | E30: 53862251 | F30: 41719 | G30: Barrio Alem 2 casa 46 | H30: Leandro N Alem | I30: Santiago canclini 3 grado | J30: Eva Ramona Zuetta | K30: 3764743361 | L30: Comerciante | M30: Taller de Iniciación a las Danzas Folklóricas Argentinas (Niños)
A31: 45232.345 | B31: ts330603@gmail.com | C31: Ferreira Da Silva Noah | D31: 4 | E31: 57603649 | F31: 43583 | G31: Brasil 1228 | H31: Leandro N Alem | I31: Instituto Canclini sala de 5 | J31: Tatiana Micaela Solis | K31: 3754475766 | L31: Auxiliar de maestra jardinera | M31: Taller de Iniciación a las Danzas Folklóricas Argentinas (Niños)
A32: 45232.346 | B32: ts330603@gmail.com | C32: Ferreira Da Silva Madelyn | D32: 4 | E32: 57603650 | F32: 43583 | G32: Brasil 1228 | H32: Leandro N Alem | I32: Instituto Canclini sala de 5 | J32: Tatiana Micaela Solis | K32: 3754475766 | L32: Auxiliar de maestra jardinera | M32: Taller de Iniciación a las Danzas Folklóricas Argentinas (Niños)
A33: 45242.648 | B33: jeniferbarboza29@gmail.com | C33: Yenifer Barboza | D33: 29 | E33: 37581798 | F33: 34359 | G33: B.Humberto Perez | H33: Leandro N Alem | J33: Blanca Gomez | K33: 3754432386 | L33: Empleada Domestica | M33: Danzas Folklóricas Argentina modalidad Acelerada (Mayores de 18 años) | N33: Primero
A34: 45242.65 | B34: jeniferbarboza29@gmail.com | C34: Gonzalez Agustina | D34: 12 | E34: 51377537 | F34: 40848 | G34: B.HUMBERTO PEREZ | H34: Leandro N Alem | I34: 552 | J34: Barboza yenifer | K34: 3754432386 | L34: Estudio | M34: Taller de Iniciación a las Danzas Folklóricas Argentinas (Niños)
C35: Dallabrida Ana Paula | D35: 6 | R35: =B35 | S35: Misiones
R36: =B36 | S36: Misiones
R37: =B37 | S37: Misiones
R38: =B38 | S38: Misiones
R39: =B39 | S39: Misiones
R40: =B40 | S40: Misiones
R41: =B41 | S41: Misiones
R42: =B42 | S42: Misiones
R43: =B43 | S43: Misiones
R44: =B44 | S44: Misiones
R45: =B45 | S45: Misiones
R46: =B46 | S46: Misiones

Sheet Analíticos
E2: Sede Central:
E3: Leandro N. Alem - Misiones
E4: Cataratas del Iguazú 912
E5: Tel: 3754-499750
E6: e-mail: idearmisiones@gmail.com
B8: CERTIFICADO ANALITICO
B10: El Instituto para el desarrollo del Arte, registrado en el Servicio Provincial de Enseñanza Privada de la Prov. de Misiones Nº 213/21,
B11: No incorporado a la enseñanza oficial, con sede central en calle cataratas del iguazú 912 de la ciudad de Leandro N. Alem,
B12: provincia de Misiones, Argentina, certifica que el/la alumno/a: _______________________________________, DNI: ____________________
B13: ha cursado y aprobado las siguientes materias del instructorado en "Danzas Folkloricas Argentinas"
B16: ASIGNATURAS | D16: CALIFICACIONES
D17: EN Nº | E17: EN LETRAS
B18: 1er AÑO | C18: TEORIA I
C19: ZAPATEO I
C20: ZARANDEO I
C21: ACEPTACION COMPOSITIVA COREOGRAFIA I
C22: INTERPRETACION TEATRALIDAD Y EXPRESION I
C23: TALLER GESTION Y ORG. PARA LA PUESTA EN ESCENA
B27: ASIGNATURAS | D27: CALIFICACIONES
D28: EN NRO | E28: EN LETRAS
B29: 2do AÑO | C29: TEORIA II
C30: ZAPATEO II
C31: ZARANDEO II
C32: ACEPTACION COMPOSITIVA COREOGRAFIA II
C33: INTERPRETACION TEATRALIDAD Y EXPRESION II
C34: HISTORIA DE LA DANZA
C35: DIDACTICA APLICADA
C36: USO DIDACTICO DE LAS TIC
B38: ASIGNATURAS | D38: CALIFICACIONES
D39: EN NRO | E39: EN LETRAS
B40: 3er AÑO | C40: TEORIA III
C41: ZAPATEO III
C42: ZARANDEO III
C43: ACEPTACION COMPOSITIVA COREOGRAFIA III
C44: INTERPRETACION TEATRALIDAD Y EXPRESION III
C45: METODOLOGIA Y TECNICA DE LA INVESTIGACIÓN
C46: PRACTICAS EDUCATIVAS
B50: El alumno/a ha egresado, como "Maestro Preparatorio de Danzas Folklóricas Argentinas"
B51: y ha sido registrado en esta institución bajo el Nro 1/23, en la ciudad de L. N. Alem, Mnes. el día 19 de Julio de 2023.
C56: SELLO | D56: ___________________

Sheet Config
A1: Forma de Pago | B1: Período | C1: Detalle | D1: montos
A2: Efectivo | B2: Enero | C2: 1er Año Preparatorio | D2: 20000
A3: Mercado Pago | B3: Febrero | C3: 2do Año Preparatorio | D3: 20000
A4: Transferencia | B4: Marzo | C4: 3er Año Preparatorio | D4: 20000
A5: Cange | B5: Abril
A6: BECA 2022 | B6: Mayo | C6: Derecho de Examen 1ro Preparatorio | D6: 40000
B7: Junio | C7: Derecho de Examen 2do Preparatorio | D7: 45000
B8: Julio | C8: Derecho de Examen 3ro Preparatorio | D8: 50000
B9: Agosto | C9: Derecho de Examen 1ro Preparatorio | D9: 55000
B10: Septiembre | C10: Derecho de Examen 2do Preparatorio | D10: 60000
B11: Octubre | C11: Derecho de Examen 3ro Preparatorio | D11: 65000
B12: Noviembre | C12: Derecho de Examen DIPLOMA Preparatorio | D12: 80000
B13: Diciembre | C13: Derecho de Examen 1ro Superior | D13: 85000
B14: EXAMEN | C14: Derecho de Examen 2do Superior | D14: 90000
C15: Derecho de Examen 3ro Superior | D15: 95000
C16: Matrícula 2025 | D16: 10000
C17: Taller de Folklore "Un lenguaje Artístico" | D17: 18000
C18: Taller "Paisanitos" Danzas Folkloricas Argentinas | D18: 18000
C19: Taller de Malambo | D19: 18000
C20: Inscripción Danzas Folkloricas Argentinas Infantiles | D20: 15000
C21: Inscripción Danzas Folkloricas Argentinas Adultos | D21: 15000
C22: Ballet "Bailar y Vivir" | D22: 15000

Sheet Insc
F5: Reg. Nro. 213/21
B9: Instituto Superior de Danzas
B10: Sede Central: Cataratas del Iguazú 912 - L. N. Alem - Misiones - Argentina - e-mail: idearmisiones@gmail.com
B11: SOLICITUD DE MATRICULA CICLO 2026
G12: =TODAY() -> 46197
B13: DATOS DEL ALUMNO
B15: Apellido y Nombres: | C15: Yanina Belen Karuchek | E15: Domicilio: | F15: =VLOOKUP(C15,formulario!C2:H1001,4,FALSE) -> #N/A
B16: Edad: | C16: =VLOOKUP(C15,formulario!C2:E1001,3,FALSE) -> #N/A | E16: Localidad: | F16: =VLOOKUP(C15,formulario!C2:I1001,7,FALSE) -> #N/A
B17: DNI: | C17: =VLOOKUP(C15,formulario!C2:T1001,20,FALSE) -> #REF! | E17: Provincia: | F17: Misiones
B18: Fecha de Nacimiento: | C18: =VLOOKUP(C15,formulario!C2:H1001,6,FALSE) -> #N/A | E18: Nacionalidad: | F18: Argentina
B19: Teléfono: | C19: =VLOOKUP(C15,formulario!C2:H1001,5,FALSE) -> #N/A | E19: e-mail: | F19: =VLOOKUP(C15,formulario!C2:O1001,19,FALSE) -> #REF!
B20: Cursada | C20: =VLOOKUP(C15,formulario!C2:T1001,8,FALSE) -> #N/A
B21: Solicitud de Insc. Nivel: | C21: Preparatorios | E21: Preparatorioes | G21: Superiores
C22: =VLOOKUP(C15,formulario!C2:T1001,9,FALSE) -> #N/A | E22: =VLOOKUP(C15,formulario!C2:T1001,10,FALSE) -> #N/A | G22: =VLOOKUP(C15,formulario!C2:T1001,11,FALSE) -> #N/A
B24: EL RESPONSABLE manifiesta saber y haber tomado conocimiento del Reglamento interno y toda normativa,
B25: Resolución o Disposición que dispongan las autoridades del Instituto Para el Desarrollo del Arte (IDeAr)
B26: Con sede central en Leandro N. Alem y filiales, con lo que declara estar plenamente de acuerdo comprome-
B27: tiéndose a colaborar con su cumplimiento institucional y personal, como también en las participaciones
B28: previstas, autorizando publicaciones de fotografías relativas en medios gráficos y redes sociales
B29: Asímismo acepta responsabilizarse con el aporte económico por los servicios educativos establecidos.
B30: El presente contrato no modifica sino que complementa e integra la reglamentación nominada.
B31: Aranceles de la inscripción y/o Matrícula: | D31: 5000
B38: --------------------------------- | F38: ------------------------------------
B39: FIRMA/SELLO DE CAJA | F39: Firma Responsable/Tutor
F40: ACEPTO
A43: Cuerpo: | B43: ="Hola, Envío Solicitud de matrícula para el año en curso, por favor imprimir y presentar al inicio de clases. En caso de Alumno nuevo, adjuntar fotocopia de DNI y carpeta transparente. Saludos Cordiales" -> Hola, Envío Solicitud de matrícula para el año en curso, por favor imprimir y presentar al inicio de clases. En caso de Alumno nuevo, adjuntar fotocopia de DNI y carpeta transparente. Saludos Cordiales
A44: Asunto: | B44: ="Solicitud de Matrícula - Instituto Superior de Danzas Folkloricas Argentinas" -> Solicitud de Matrícula - Instituto Superior de Danzas Folkloricas Argentinas
A45: Adjunto: | B45: =D12

Sheet Boletines Preparatorio
C4: BOLETÍN DE CALIFICACIONES
C5: "Danzas Folklóricas Argentinas"
C6: Reg. SPEPM: 213/21
B8: Alumno:
B10: Nivel | C10: Fecha | D10: Zapateo | E10: Zarandeo | F10: Teoría | G10: Posición | H10: Expresión | I10: Danza | J10: Final | K10: Firma
B12: Primer año Preparatorio
B14: Observaciones:
B16: Segundo año Preparatorio
B18: Observaciones:
B20: Tercer año Preparatorio
B22: Observaciones:
C28: BOLETÍN DE CALIFICACIONES
C29: "Danzas Folklóricas Argentinas"
C30: Reg. SPEPM: 213/21
B32: Alumno:
B34: Nivel | C34: Fecha | D34: Zapateo | E34: Zarandeo | F34: Teoría | G34: Posición | H34: Expresión | I34: Danza | J34: Final | K34: Firma
B36: Primer año Preparatorio
B38: Observaciones:
B40: Segundo año Preparatorio
B42: Observaciones:
B44: Tercer año Preparatorio
B46: Observaciones:

Sheet Boletines Elemental
C4: BOLETÍN DE CALIFICACIONES
C5: "Danzas Folklóricas Argentinas"
C6: Reg. SPEPM: 213/21
B8: Alumno:
B10: Nivel | C10: Fecha | D10: Zapateo | E10: Zarandeo | F10: Teoría | G10: Posición | H10: Expresión | I10: Danza | J10: Final | K10: Firma
B12: Primer año Elemental
B14: Observaciones:
B16: Segundo año Elemental
B18: Observaciones:
B20: Tercer año Elemental
B22: Observaciones:
C27: BOLETÍN DE CALIFICACIONES
C28: "Danzas Folklóricas Argentinas"
C29: Reg. SPEPM: 213/21
B31: Alumno:
B33: Nivel | C33: Fecha | D33: Zapateo | E33: Zarandeo | F33: Teoría | G33: Posición | H33: Expresión | I33: Danza | J33: Final | K33: Firma
B35: Primer año Elemental
B37: Observaciones:
B39: Segundo año Elemental
B41: Observaciones:
B43: Tercer año Elemental
B45: Observaciones:
